{
"meta":{"test_sets":[],"test_metrics":[],"learn_metrics":[{"best_value":"Min","name":"RMSE"}],"launch_mode":"Train","parameters":"","iteration_count":1000,"learn_sets":["learn"],"name":"experiment"},
"iterations":[
{"learn":[14.61707789],"iteration":0,"passed_time":0.1552182199,"remaining_time":155.0630017},
{"learn":[14.23010492],"iteration":1,"passed_time":0.1564375853,"remaining_time":78.06235508},
{"learn":[13.87204843],"iteration":2,"passed_time":0.1573414337,"remaining_time":52.28980313},
{"learn":[13.55418866],"iteration":3,"passed_time":0.1579732266,"remaining_time":39.33533342},
{"learn":[13.1985856],"iteration":4,"passed_time":0.1588620747,"remaining_time":31.61355287},
{"learn":[12.85125146],"iteration":5,"passed_time":0.1596733525,"remaining_time":26.45255207},
{"learn":[12.57514974],"iteration":6,"passed_time":0.1603362908,"remaining_time":22.74484811},
{"learn":[12.28236626],"iteration":7,"passed_time":0.1609791561,"remaining_time":19.96141535},
{"learn":[12.01948822],"iteration":8,"passed_time":0.1615630817,"remaining_time":17.78989044},
{"learn":[11.75218163],"iteration":9,"passed_time":0.1621750689,"remaining_time":16.05533182},
{"learn":[11.51345253],"iteration":10,"passed_time":0.1627590078,"remaining_time":14.63351443},
{"learn":[11.28309294],"iteration":11,"passed_time":0.1631991313,"remaining_time":13.43672847},
{"learn":[11.01799159],"iteration":12,"passed_time":0.1637392632,"remaining_time":12.43158867},
{"learn":[10.77654849],"iteration":13,"passed_time":0.1642354453,"remaining_time":11.56686779},
{"learn":[10.53041129],"iteration":14,"passed_time":0.1647588626,"remaining_time":10.81916531},
{"learn":[10.30933152],"iteration":15,"passed_time":0.1652351538,"remaining_time":10.16196196},
{"learn":[10.10029937],"iteration":16,"passed_time":0.165696957,"remaining_time":9.581182869},
{"learn":[9.897330564],"iteration":17,"passed_time":0.1661609145,"remaining_time":9.065001},
{"learn":[9.707085903],"iteration":18,"passed_time":0.1666835054,"remaining_time":8.606132567},
{"learn":[9.520292546],"iteration":19,"passed_time":0.1672849836,"remaining_time":8.196964199},
{"learn":[9.332907],"iteration":20,"passed_time":0.1677679112,"remaining_time":7.82118024},
{"learn":[9.172299475],"iteration":21,"passed_time":0.1682477729,"remaining_time":7.479378266},
{"learn":[8.99281824],"iteration":22,"passed_time":0.168718022,"remaining_time":7.166848153},
{"learn":[8.822538232],"iteration":23,"passed_time":0.169247483,"remaining_time":6.882730974},
{"learn":[8.677605067],"iteration":24,"passed_time":0.1698426583,"remaining_time":6.623863673},
{"learn":[8.524526186],"iteration":25,"passed_time":0.1702203285,"remaining_time":6.376715382},
{"learn":[8.385278224],"iteration":26,"passed_time":0.1705996486,"remaining_time":6.147905856},
{"learn":[8.243665979],"iteration":27,"passed_time":0.1710686884,"remaining_time":5.938527327},
{"learn":[8.114019444],"iteration":28,"passed_time":0.1715586096,"remaining_time":5.744255516},
{"learn":[7.986713773],"iteration":29,"passed_time":0.1720724428,"remaining_time":5.563675652},
{"learn":[7.880910296],"iteration":30,"passed_time":0.1725445397,"remaining_time":5.393408353},
{"learn":[7.768868545],"iteration":31,"passed_time":0.1730690487,"remaining_time":5.235338723},
{"learn":[7.666719675],"iteration":32,"passed_time":0.1735746468,"remaining_time":5.086263136},
{"learn":[7.561722363],"iteration":33,"passed_time":0.1740860177,"remaining_time":4.946090973},
{"learn":[7.465133369],"iteration":34,"passed_time":0.1745827345,"remaining_time":4.813495393},
{"learn":[7.370205773],"iteration":35,"passed_time":0.1750715383,"remaining_time":4.688026749},
{"learn":[7.27563627],"iteration":36,"passed_time":0.1755928563,"remaining_time":4.570160015},
{"learn":[7.192916639],"iteration":37,"passed_time":0.1760842862,"remaining_time":4.457712718},
{"learn":[7.115014173],"iteration":38,"passed_time":0.1764317854,"remaining_time":4.347460148},
{"learn":[7.038312567],"iteration":39,"passed_time":0.1768916597,"remaining_time":4.245399833},
{"learn":[6.956931328],"iteration":40,"passed_time":0.1773583208,"remaining_time":4.148454382},
{"learn":[6.879902146],"iteration":41,"passed_time":0.1778223415,"remaining_time":4.056042932},
{"learn":[6.806532832],"iteration":42,"passed_time":0.1783761178,"remaining_time":3.969905692},
{"learn":[6.746791938],"iteration":43,"passed_time":0.1789219808,"remaining_time":3.887486674},
{"learn":[6.684427175],"iteration":44,"passed_time":0.1793406542,"remaining_time":3.806007217},
{"learn":[6.626932542],"iteration":45,"passed_time":0.1799253758,"remaining_time":3.731495838},
{"learn":[6.56644894],"iteration":46,"passed_time":0.1804525729,"remaining_time":3.658963872},
{"learn":[6.52350486],"iteration":47,"passed_time":0.1808585003,"remaining_time":3.587026923},
{"learn":[6.470018155],"iteration":48,"passed_time":0.1815296041,"remaining_time":3.523156193},
{"learn":[6.417194162],"iteration":49,"passed_time":0.1820228312,"remaining_time":3.458433793},
{"learn":[6.367805003],"iteration":50,"passed_time":0.1825244503,"remaining_time":3.396386339},
{"learn":[6.320582196],"iteration":51,"passed_time":0.183062342,"remaining_time":3.337367311},
{"learn":[6.269927738],"iteration":52,"passed_time":0.183546372,"remaining_time":3.279592722},
{"learn":[6.232449724],"iteration":53,"passed_time":0.1840453846,"remaining_time":3.224202479},
{"learn":[6.192098289],"iteration":54,"passed_time":0.1845264945,"remaining_time":3.170500678},
{"learn":[6.15312448],"iteration":55,"passed_time":0.1849880936,"remaining_time":3.118370721},
{"learn":[6.113499619],"iteration":56,"passed_time":0.1854605791,"remaining_time":3.06823379},
{"learn":[6.079045274],"iteration":57,"passed_time":0.185932545,"remaining_time":3.01980099},
{"learn":[6.046031129],"iteration":58,"passed_time":0.1864313628,"remaining_time":2.973422244},
{"learn":[6.016783737],"iteration":59,"passed_time":0.186864052,"remaining_time":2.927536814},
{"learn":[5.990195819],"iteration":60,"passed_time":0.1872791413,"remaining_time":2.882870716},
{"learn":[5.962463604],"iteration":61,"passed_time":0.1876884527,"remaining_time":2.839544656},
{"learn":[5.934607066],"iteration":62,"passed_time":0.1882493216,"remaining_time":2.799835148},
{"learn":[5.908895873],"iteration":63,"passed_time":0.1887217526,"remaining_time":2.760055631},
{"learn":[5.885345316],"iteration":64,"passed_time":0.1892144599,"remaining_time":2.721777231},
{"learn":[5.860395386],"iteration":65,"passed_time":0.1896557059,"remaining_time":2.683915595},
{"learn":[5.838607985],"iteration":66,"passed_time":0.1901318714,"remaining_time":2.647657254},
{"learn":[5.811640963],"iteration":67,"passed_time":0.1906122974,"remaining_time":2.612509723},
{"learn":[5.788115623],"iteration":68,"passed_time":0.1911062593,"remaining_time":2.578549672},
{"learn":[5.764504698],"iteration":69,"passed_time":0.1915906451,"remaining_time":2.54541857},
{"learn":[5.745916478],"iteration":70,"passed_time":0.1920608974,"remaining_time":2.513022165},
{"learn":[5.72694025],"iteration":71,"passed_time":0.1925540533,"remaining_time":2.481807799},
{"learn":[5.706952853],"iteration":72,"passed_time":0.1931417628,"remaining_time":2.452635809},
{"learn":[5.693458548],"iteration":73,"passed_time":0.1936839112,"remaining_time":2.423666241},
{"learn":[5.673624935],"iteration":74,"passed_time":0.194217593,"remaining_time":2.395350313},
{"learn":[5.656518427],"iteration":75,"passed_time":0.1946783673,"remaining_time":2.366879097},
{"learn":[5.642566644],"iteration":76,"passed_time":0.1950092568,"remaining_time":2.337578493},
{"learn":[5.628036262],"iteration":77,"passed_time":0.1955590008,"remaining_time":2.311607676},
{"learn":[5.610460092],"iteration":78,"passed_time":0.1960719188,"remaining_time":2.285851104},
{"learn":[5.597342844],"iteration":79,"passed_time":0.1965851613,"remaining_time":2.260729355},
{"learn":[5.582851272],"iteration":80,"passed_time":0.1971218544,"remaining_time":2.236481286},
{"learn":[5.569860385],"iteration":81,"passed_time":0.1976811261,"remaining_time":2.213064314},
{"learn":[5.556181596],"iteration":82,"passed_time":0.1981844048,"remaining_time":2.189579508},
{"learn":[5.542202197],"iteration":83,"passed_time":0.1987060188,"remaining_time":2.166841824},
{"learn":[5.530573202],"iteration":84,"passed_time":0.1991991455,"remaining_time":2.144320213},
{"learn":[5.519327094],"iteration":85,"passed_time":0.1997211581,"remaining_time":2.12261789},
{"learn":[5.507372201],"iteration":86,"passed_time":0.2002403927,"remaining_time":2.101373316},
{"learn":[5.497670568],"iteration":87,"passed_time":0.200803541,"remaining_time":2.081054879},
{"learn":[5.489001593],"iteration":88,"passed_time":0.2013161552,"remaining_time":2.060663117},
{"learn":[5.479790097],"iteration":89,"passed_time":0.2018431906,"remaining_time":2.040858927},
{"learn":[5.47320855],"iteration":90,"passed_time":0.2023525801,"remaining_time":2.021302147},
{"learn":[5.466429029],"iteration":91,"passed_time":0.2027345904,"remaining_time":2.000902261},
{"learn":[5.458171489],"iteration":92,"passed_time":0.2031983585,"remaining_time":1.981730227},
{"learn":[5.447648504],"iteration":93,"passed_time":0.2037317897,"remaining_time":1.963627675},
{"learn":[5.437677992],"iteration":94,"passed_time":0.2044350813,"remaining_time":1.947513143},
{"learn":[5.42918398],"iteration":95,"passed_time":0.2048830332,"remaining_time":1.929315229},
{"learn":[5.418549452],"iteration":96,"passed_time":0.205403622,"remaining_time":1.912159491},
{"learn":[5.413546501],"iteration":97,"passed_time":0.2059723353,"remaining_time":1.895786188},
{"learn":[5.405506797],"iteration":98,"passed_time":0.2065626519,"remaining_time":1.879928782},
{"learn":[5.398604035],"iteration":99,"passed_time":0.2070568443,"remaining_time":1.863511599},
{"learn":[5.390591683],"iteration":100,"passed_time":0.2075416976,"remaining_time":1.847326595},
{"learn":[5.383561744],"iteration":101,"passed_time":0.2080527611,"remaining_time":1.831680191},
{"learn":[5.377393803],"iteration":102,"passed_time":0.2085557844,"remaining_time":1.816257656},
{"learn":[5.368400168],"iteration":103,"passed_time":0.2090518249,"remaining_time":1.801061876},
{"learn":[5.358004104],"iteration":104,"passed_time":0.2096702067,"remaining_time":1.787188904},
{"learn":[5.350451615],"iteration":105,"passed_time":0.2102191627,"remaining_time":1.772980486},
{"learn":[5.343755627],"iteration":106,"passed_time":0.2106770369,"remaining_time":1.758267233},
{"learn":[5.339655086],"iteration":107,"passed_time":0.2112046742,"remaining_time":1.744394161},
{"learn":[5.330546215],"iteration":108,"passed_time":0.2117541765,"remaining_time":1.73094469},
{"learn":[5.325613844],"iteration":109,"passed_time":0.2122201337,"remaining_time":1.717053809},
{"learn":[5.320289701],"iteration":110,"passed_time":0.2126934915,"remaining_time":1.70346409},
{"learn":[5.313739802],"iteration":111,"passed_time":0.2131364531,"remaining_time":1.689867592},
{"learn":[5.309974522],"iteration":112,"passed_time":0.2136155816,"remaining_time":1.676787796},
{"learn":[5.304805976],"iteration":113,"passed_time":0.2140728403,"remaining_time":1.663759092},
{"learn":[5.300511532],"iteration":114,"passed_time":0.2159429387,"remaining_time":1.661821746},
{"learn":[5.294776286],"iteration":115,"passed_time":0.2164755603,"remaining_time":1.649693063},
{"learn":[5.287415818],"iteration":116,"passed_time":0.2169703154,"remaining_time":1.637476825},
{"learn":[5.279143128],"iteration":117,"passed_time":0.2175962895,"remaining_time":1.626440063},
{"learn":[5.275662395],"iteration":118,"passed_time":0.2181493551,"remaining_time":1.615038503},
{"learn":[5.268149418],"iteration":119,"passed_time":0.2186422025,"remaining_time":1.603376152},
{"learn":[5.262785259],"iteration":120,"passed_time":0.2191518465,"remaining_time":1.592020439},
{"learn":[5.259098282],"iteration":121,"passed_time":0.2197984436,"remaining_time":1.581828143},
{"learn":[5.253259323],"iteration":122,"passed_time":0.2205125406,"remaining_time":1.572272342},
{"learn":[5.25080388],"iteration":123,"passed_time":0.2210180427,"remaining_time":1.561385528},
{"learn":[5.246702785],"iteration":124,"passed_time":0.2216661733,"remaining_time":1.551663213},
{"learn":[5.241227441],"iteration":125,"passed_time":0.2222950856,"remaining_time":1.541951625},
{"learn":[5.238430635],"iteration":126,"passed_time":0.2229388093,"remaining_time":1.532484886},
{"learn":[5.232463062],"iteration":127,"passed_time":0.2234497639,"remaining_time":1.522251517},
{"learn":[5.226119474],"iteration":128,"passed_time":0.2239280873,"remaining_time":1.511948558},
{"learn":[5.221797237],"iteration":129,"passed_time":0.2243844475,"remaining_time":1.501649764},
{"learn":[5.216775716],"iteration":130,"passed_time":0.224865908,"remaining_time":1.491667741},
{"learn":[5.212220841],"iteration":131,"passed_time":0.2254370344,"remaining_time":1.482419287},
{"learn":[5.209153395],"iteration":132,"passed_time":0.2260731225,"remaining_time":1.473724791},
{"learn":[5.207312912],"iteration":133,"passed_time":0.2267924292,"remaining_time":1.465688386},
{"learn":[5.200757246],"iteration":134,"passed_time":0.2274811828,"remaining_time":1.457564616},
{"learn":[5.197078713],"iteration":135,"passed_time":0.2279409939,"remaining_time":1.448095726},
{"learn":[5.191987439],"iteration":136,"passed_time":0.2284798916,"remaining_time":1.439256544},
{"learn":[5.18608639],"iteration":137,"passed_time":0.2289854025,"remaining_time":1.430329109},
{"learn":[5.182612204],"iteration":138,"passed_time":0.2295805527,"remaining_time":1.4220781},
{"learn":[5.180029399],"iteration":139,"passed_time":0.2302093385,"remaining_time":1.41414308},
{"learn":[5.176996781],"iteration":140,"passed_time":0.2306955728,"remaining_time":1.405443241},
{"learn":[5.172737752],"iteration":141,"passed_time":0.2313256553,"remaining_time":1.397728255},
{"learn":[5.166503876],"iteration":142,"passed_time":0.2319468784,"remaining_time":1.390059264},
{"learn":[5.162300887],"iteration":143,"passed_time":0.2325555561,"remaining_time":1.382413583},
{"learn":[5.160240281],"iteration":144,"passed_time":0.2330436672,"remaining_time":1.374154038},
{"learn":[5.157335209],"iteration":145,"passed_time":0.233666255,"remaining_time":1.366787546},
{"learn":[5.156069682],"iteration":146,"passed_time":0.2340419887,"remaining_time":1.358080383},
{"learn":[5.153964906],"iteration":147,"passed_time":0.2346199439,"remaining_time":1.350649947},
{"learn":[5.151074137],"iteration":148,"passed_time":0.2352181651,"remaining_time":1.343427238},
{"learn":[5.150185298],"iteration":149,"passed_time":0.2355830301,"remaining_time":1.334970504},
{"learn":[5.146434279],"iteration":150,"passed_time":0.2360573119,"remaining_time":1.327236145},
{"learn":[5.143011193],"iteration":151,"passed_time":0.2365881327,"remaining_time":1.31991274},
{"learn":[5.136919897],"iteration":152,"passed_time":0.2371592115,"remaining_time":1.312900994},
{"learn":[5.133658855],"iteration":153,"passed_time":0.2376489074,"remaining_time":1.305525816},
{"learn":[5.12998326],"iteration":154,"passed_time":0.2381670182,"remaining_time":1.29839439},
{"learn":[5.125818564],"iteration":155,"passed_time":0.2386249748,"remaining_time":1.2910223},
{"learn":[5.122806157],"iteration":156,"passed_time":0.2392098589,"remaining_time":1.284419816},
{"learn":[5.120770888],"iteration":157,"passed_time":0.2397410931,"remaining_time":1.277607597},
{"learn":[5.117565306],"iteration":158,"passed_time":0.2403604337,"remaining_time":1.271340407},
{"learn":[5.111908563],"iteration":159,"passed_time":0.2410565083,"remaining_time":1.265546669},
{"learn":[5.105275133],"iteration":160,"passed_time":0.2418411164,"remaining_time":1.260277619},
{"learn":[5.101289799],"iteration":161,"passed_time":0.242452611,"remaining_time":1.254168445},
{"learn":[5.098275521],"iteration":162,"passed_time":0.2429270418,"remaining_time":1.247422908},
{"learn":[5.095616243],"iteration":163,"passed_time":0.2434928533,"remaining_time":1.241219667},
{"learn":[5.093605994],"iteration":164,"passed_time":0.244029999,"remaining_time":1.234939692},
{"learn":[5.092920592],"iteration":165,"passed_time":0.2444436941,"remaining_time":1.22810868},
{"learn":[5.091378765],"iteration":166,"passed_time":0.2449576078,"remaining_time":1.221854415},
{"learn":[5.088453733],"iteration":167,"passed_time":0.2456644042,"remaining_time":1.216623716},
{"learn":[5.08812929],"iteration":168,"passed_time":0.245951638,"remaining_time":1.209383498},
{"learn":[5.087649881],"iteration":169,"passed_time":0.2462720121,"remaining_time":1.202386883},
{"learn":[5.085970322],"iteration":170,"passed_time":0.2468132502,"remaining_time":1.19653909},
{"learn":[5.083270411],"iteration":171,"passed_time":0.2474933045,"remaining_time":1.191421256},
{"learn":[5.079130579],"iteration":172,"passed_time":0.2481675729,"remaining_time":1.186327068},
{"learn":[5.07430597],"iteration":173,"passed_time":0.2487315364,"remaining_time":1.180760052},
{"learn":[5.072405665],"iteration":174,"passed_time":0.249244091,"remaining_time":1.175007857},
{"learn":[5.070429553],"iteration":175,"passed_time":0.2498096348,"remaining_time":1.16956329},
{"learn":[5.066957206],"iteration":176,"passed_time":0.2504205547,"remaining_time":1.164384839},
{"learn":[5.062706439],"iteration":177,"passed_time":0.2509588138,"remaining_time":1.158922162},
{"learn":[5.057599286],"iteration":178,"passed_time":0.2515386999,"remaining_time":1.153705434},
{"learn":[5.054350175],"iteration":179,"passed_time":0.2522077323,"remaining_time":1.148946336},
{"learn":[5.051668659],"iteration":180,"passed_time":0.2527753174,"remaining_time":1.143773398},
{"learn":[5.049384697],"iteration":181,"passed_time":0.2534292387,"remaining_time":1.139039106},
{"learn":[5.045534061],"iteration":182,"passed_time":0.2539743097,"remaining_time":1.133863448},
{"learn":[5.043667883],"iteration":183,"passed_time":0.2546563282,"remaining_time":1.129345455},
{"learn":[5.040029697],"iteration":184,"passed_time":0.2552066965,"remaining_time":1.12428896},
{"learn":[5.037689644],"iteration":185,"passed_time":0.2558484612,"remaining_time":1.1196809},
{"learn":[5.031433324],"iteration":186,"passed_time":0.2564758521,"remaining_time":1.115052769},
{"learn":[5.024299669],"iteration":187,"passed_time":0.2572623899,"remaining_time":1.111154578},
{"learn":[5.022565662],"iteration":188,"passed_time":0.257904091,"remaining_time":1.106667819},
{"learn":[5.018861329],"iteration":189,"passed_time":0.2585768507,"remaining_time":1.102353942},
{"learn":[5.017169026],"iteration":190,"passed_time":0.259190834,"remaining_time":1.097829239},
{"learn":[5.015400461],"iteration":191,"passed_time":0.2598972919,"remaining_time":1.093734437},
{"learn":[5.012346683],"iteration":192,"passed_time":0.2604705397,"remaining_time":1.089117749},
{"learn":[5.008887078],"iteration":193,"passed_time":0.2610535277,"remaining_time":1.084583213},
{"learn":[5.006583256],"iteration":194,"passed_time":0.2616054032,"remaining_time":1.079960767},
{"learn":[5.002624734],"iteration":195,"passed_time":0.2623115229,"remaining_time":1.076012574},
{"learn":[4.9997245],"iteration":196,"passed_time":0.2628922322,"remaining_time":1.071586104},
{"learn":[4.995887681],"iteration":197,"passed_time":0.2634696408,"remaining_time":1.067185111},
{"learn":[4.990738108],"iteration":198,"passed_time":0.2640114351,"remaining_time":1.062679194},
{"learn":[4.987794915],"iteration":199,"passed_time":0.264615778,"remaining_time":1.058463112},
{"learn":[4.984446273],"iteration":200,"passed_time":0.265137027,"remaining_time":1.05395266},
{"learn":[4.979153523],"iteration":201,"passed_time":0.2657322108,"remaining_time":1.049773783},
{"learn":[4.973027787],"iteration":202,"passed_time":0.2663189689,"remaining_time":1.045597134},
{"learn":[4.971311415],"iteration":203,"passed_time":0.2670149851,"remaining_time":1.041882001},
{"learn":[4.970365669],"iteration":204,"passed_time":0.2675072702,"remaining_time":1.037406243},
{"learn":[4.967865244],"iteration":205,"passed_time":0.2681241377,"remaining_time":1.033449346},
{"learn":[4.965501677],"iteration":206,"passed_time":0.2686776707,"remaining_time":1.029282091},
{"learn":[4.962328558],"iteration":207,"passed_time":0.2692883301,"remaining_time":1.025367103},
{"learn":[4.958073189],"iteration":208,"passed_time":0.2698699631,"remaining_time":1.021373879},
{"learn":[4.956355982],"iteration":209,"passed_time":0.2703979589,"remaining_time":1.017211369},
{"learn":[4.951900962],"iteration":210,"passed_time":0.2713881902,"remaining_time":1.014811763},
{"learn":[4.950467442],"iteration":211,"passed_time":0.2720732432,"remaining_time":1.011291112},
{"learn":[4.94898352],"iteration":212,"passed_time":0.2726908751,"remaining_time":1.007547975},
{"learn":[4.945912668],"iteration":213,"passed_time":0.2733187537,"remaining_time":1.003871684},
{"learn":[4.942173244],"iteration":214,"passed_time":0.2740167104,"remaining_time":1.000479617},
{"learn":[4.941623492],"iteration":215,"passed_time":0.2745745438,"remaining_time":0.9966038999},
{"learn":[4.939001526],"iteration":216,"passed_time":0.2752217624,"remaining_time":0.99308129},
{"learn":[4.93706297],"iteration":217,"passed_time":0.2758463343,"remaining_time":0.9895038229},
{"learn":[4.935797834],"iteration":218,"passed_time":0.2764591406,"remaining_time":0.9859113646},
{"learn":[4.932850985],"iteration":219,"passed_time":0.2770507899,"remaining_time":0.9822709824},
{"learn":[4.929526101],"iteration":220,"passed_time":0.2775839658,"remaining_time":0.9784520785},
{"learn":[4.928935139],"iteration":221,"passed_time":0.278056903,"remaining_time":0.9744516691},
{"learn":[4.928560494],"iteration":222,"passed_time":0.2787219423,"remaining_time":0.9711522383},
{"learn":[4.924704117],"iteration":223,"passed_time":0.2792333736,"remaining_time":0.967344187},
{"learn":[4.924318252],"iteration":224,"passed_time":0.2798467606,"remaining_time":0.9639166199},
{"learn":[4.920673149],"iteration":225,"passed_time":0.2804058066,"remaining_time":0.9603278509},
{"learn":[4.92030189],"iteration":226,"passed_time":0.2810132125,"remaining_time":0.9569304548},
{"learn":[4.915819735],"iteration":227,"passed_time":0.281584854,"remaining_time":0.9534364353},
{"learn":[4.913347902],"iteration":228,"passed_time":0.2822249275,"remaining_time":0.9501983367},
{"learn":[4.909535358],"iteration":229,"passed_time":0.2827789836,"remaining_time":0.946694858},
{"learn":[4.908925937],"iteration":230,"passed_time":0.2832538217,"remaining_time":0.9429531986},
{"learn":[4.906354447],"iteration":231,"passed_time":0.2837739294,"remaining_time":0.9393895595},
{"learn":[4.902956681],"iteration":232,"passed_time":0.2846535521,"remaining_time":0.9370355126},
{"learn":[4.902392072],"iteration":233,"passed_time":0.2851866011,"remaining_time":0.9335595574},
{"learn":[4.900387276],"iteration":234,"passed_time":0.2858875308,"remaining_time":0.9306551533},
{"learn":[4.897034051],"iteration":235,"passed_time":0.2864518228,"remaining_time":0.9273270874},
{"learn":[4.895583593],"iteration":236,"passed_time":0.2873959213,"remaining_time":0.9252450967},
{"learn":[4.893521962],"iteration":237,"passed_time":0.287895036,"remaining_time":0.9217479723},
{"learn":[4.888174577],"iteration":238,"passed_time":0.2885549492,"remaining_time":0.9187879345},
{"learn":[4.88485815],"iteration":239,"passed_time":0.2892775515,"remaining_time":0.9160455796},
{"learn":[4.883259571],"iteration":240,"passed_time":0.2899258093,"remaining_time":0.9130858474},
{"learn":[4.88111363],"iteration":241,"passed_time":0.2904584865,"remaining_time":0.9097831932},
{"learn":[4.877612133],"iteration":242,"passed_time":0.2910254578,"remaining_time":0.906610171},
{"learn":[4.874579374],"iteration":243,"passed_time":0.2916257435,"remaining_time":0.9035617299},
{"learn":[4.87420568],"iteration":244,"passed_time":0.2922193085,"remaining_time":0.9005125629},
{"learn":[4.873534965],"iteration":245,"passed_time":0.2928133145,"remaining_time":0.8974847118},
{"learn":[4.871052717],"iteration":246,"passed_time":0.2934376238,"remaining_time":0.8945689504},
{"learn":[4.863606914],"iteration":247,"passed_time":0.293953544,"remaining_time":0.8913430044},
{"learn":[4.861316815],"iteration":248,"passed_time":0.294618458,"remaining_time":0.8885882007},
{"learn":[4.860813239],"iteration":249,"passed_time":0.2950993078,"remaining_time":0.8852979233},
{"learn":[4.859227599],"iteration":250,"passed_time":0.2957092424,"remaining_time":0.8824152293},
{"learn":[4.858787859],"iteration":251,"passed_time":0.2961824286,"remaining_time":0.8791446689},
{"learn":[4.858346937],"iteration":252,"passed_time":0.2967583345,"remaining_time":0.8761995092},
{"learn":[4.854539759],"iteration":253,"passed_time":0.2973232304,"remaining_time":0.8732406688},
{"learn":[4.85219599],"iteration":254,"passed_time":0.2980578791,"remaining_time":0.8707965487},
{"learn":[4.848759273],"iteration":255,"passed_time":0.2986610565,"remaining_time":0.8679836956},
{"learn":[4.84535226],"iteration":256,"passed_time":0.2993485363,"remaining_time":0.8654317607},
{"learn":[4.842884283],"iteration":257,"passed_time":0.2999163592,"remaining_time":0.8625501494},
{"learn":[4.835942701],"iteration":258,"passed_time":0.3006198949,"remaining_time":0.8600746801},
{"learn":[4.835843331],"iteration":259,"passed_time":0.3010653569,"remaining_time":0.8568783235},
{"learn":[4.829378686],"iteration":260,"passed_time":0.3016317751,"remaining_time":0.8540455243},
{"learn":[4.827427251],"iteration":261,"passed_time":0.3021211525,"remaining_time":0.8510130173},
{"learn":[4.82677259],"iteration":262,"passed_time":0.3027235936,"remaining_time":0.8483166863},
{"learn":[4.82447153],"iteration":263,"passed_time":0.3032054482,"remaining_time":0.8453000375},
{"learn":[4.821501661],"iteration":264,"passed_time":0.3038834496,"remaining_time":0.8428465488},
{"learn":[4.818495698],"iteration":265,"passed_time":0.3044720946,"remaining_time":0.8401598401},
{"learn":[4.817877764],"iteration":266,"passed_time":0.305077708,"remaining_time":0.8375354307},
{"learn":[4.809825186],"iteration":267,"passed_time":0.3056858811,"remaining_time":0.8349330781},
{"learn":[4.807921885],"iteration":268,"passed_time":0.3062231893,"remaining_time":0.832152979},
{"learn":[4.806065308],"iteration":269,"passed_time":0.3067874189,"remaining_time":0.8294622807},
{"learn":[4.799742537],"iteration":270,"passed_time":0.3074232433,"remaining_time":0.8269798684},
{"learn":[4.797854915],"iteration":271,"passed_time":0.3079809122,"remaining_time":0.8243018532},
{"learn":[4.79512263],"iteration":272,"passed_time":0.3085200513,"remaining_time":0.8215900266},
{"learn":[4.790163348],"iteration":273,"passed_time":0.3090509197,"remaining_time":0.8188721448},
{"learn":[4.78921101],"iteration":274,"passed_time":0.3097317763,"remaining_time":0.8165655921},
{"learn":[4.784463961],"iteration":275,"passed_time":0.3103575572,"remaining_time":0.8141263457},
{"learn":[4.778973812],"iteration":276,"passed_time":0.3108846854,"remaining_time":0.8114426988},
{"learn":[4.775396651],"iteration":277,"passed_time":0.311459963,"remaining_time":0.8088996162},
{"learn":[4.77288481],"iteration":278,"passed_time":0.3120280569,"remaining_time":0.8063520752},
{"learn":[4.767325231],"iteration":279,"passed_time":0.3127093862,"remaining_time":0.8041098501},
{"learn":[4.763403331],"iteration":280,"passed_time":0.3133772123,"remaining_time":0.8018441838},
{"learn":[4.763183266],"iteration":281,"passed_time":0.314113489,"remaining_time":0.7997641315},
{"learn":[4.759939653],"iteration":282,"passed_time":0.3146425817,"remaining_time":0.7971686611},
{"learn":[4.757075792],"iteration":283,"passed_time":0.3151787434,"remaining_time":0.7946055643},
{"learn":[4.755534954],"iteration":284,"passed_time":0.3158449748,"remaining_time":0.792383007},
{"learn":[4.752084104],"iteration":285,"passed_time":0.3164130158,"remaining_time":0.7899262003},
{"learn":[4.75154054],"iteration":286,"passed_time":0.3170404731,"remaining_time":0.7876301648},
{"learn":[4.748116878],"iteration":287,"passed_time":0.3177097087,"remaining_time":0.7854490021},
{"learn":[4.747922688],"iteration":288,"passed_time":0.3182439103,"remaining_time":0.7829460906},
{"learn":[4.743300007],"iteration":289,"passed_time":0.3193010949,"remaining_time":0.7817371634},
{"learn":[4.737524569],"iteration":290,"passed_time":0.3198418147,"remaining_time":0.7792709506},
{"learn":[4.737283974],"iteration":291,"passed_time":0.3203248034,"remaining_time":0.7766779481},
{"learn":[4.734037273],"iteration":292,"passed_time":0.3209337204,"remaining_time":0.7744032093},
{"learn":[4.733069473],"iteration":293,"passed_time":0.3215433189,"remaining_time":0.7721414392},
{"learn":[4.73261918],"iteration":294,"passed_time":0.3222083373,"remaining_time":0.7700233147},
{"learn":[4.730292201],"iteration":295,"passed_time":0.3228503358,"remaining_time":0.7678602581},
{"learn":[4.726632968],"iteration":296,"passed_time":0.3233959759,"remaining_time":0.7654793639},
{"learn":[4.722276334],"iteration":297,"passed_time":0.3239721832,"remaining_time":0.7631827939},
{"learn":[4.721321993],"iteration":298,"passed_time":0.3246019419,"remaining_time":0.7610232818},
{"learn":[4.718930011],"iteration":299,"passed_time":0.3252253052,"remaining_time":0.7588590455},
{"learn":[4.71874527],"iteration":300,"passed_time":0.3258327895,"remaining_time":0.7566681723},
{"learn":[4.716327888],"iteration":301,"passed_time":0.3264925535,"remaining_time":0.754608617},
{"learn":[4.714470634],"iteration":302,"passed_time":0.3270579417,"remaining_time":0.7523412057},
{"learn":[4.714321636],"iteration":303,"passed_time":0.327571251,"remaining_time":0.7499657589},
{"learn":[4.713367863],"iteration":304,"passed_time":0.3281808983,"remaining_time":0.747822047},
{"learn":[4.712915438],"iteration":305,"passed_time":0.3288140006,"remaining_time":0.745741557},
{"learn":[4.710726261],"iteration":306,"passed_time":0.3293504276,"remaining_time":0.7434522682},
{"learn":[4.705634453],"iteration":307,"passed_time":0.3299796425,"remaining_time":0.7413828331},
{"learn":[4.700591518],"iteration":308,"passed_time":0.3307882654,"remaining_time":0.7397239205},
{"learn":[4.697937808],"iteration":309,"passed_time":0.3313976206,"remaining_time":0.737626962},
{"learn":[4.694211972],"iteration":310,"passed_time":0.3319484832,"remaining_time":0.7354099836},
{"learn":[4.694069903],"iteration":311,"passed_time":0.3325773571,"remaining_time":0.7333757105},
{"learn":[4.693109809],"iteration":312,"passed_time":0.3331070413,"remaining_time":0.7311327073},
{"learn":[4.688252413],"iteration":313,"passed_time":0.3336135159,"remaining_time":0.7288499105},
{"learn":[4.68708207],"iteration":314,"passed_time":0.3341338773,"remaining_time":0.7266085904},
{"learn":[4.68417119],"iteration":315,"passed_time":0.3346717698,"remaining_time":0.7244161093},
{"learn":[4.679242431],"iteration":316,"passed_time":0.3353364041,"remaining_time":0.7225071419},
{"learn":[4.673756059],"iteration":317,"passed_time":0.3360153419,"remaining_time":0.7206366766},
{"learn":[4.672263302],"iteration":318,"passed_time":0.3365907943,"remaining_time":0.7185527616},
{"learn":[4.669236508],"iteration":319,"passed_time":0.3372465665,"remaining_time":0.7166489537},
{"learn":[4.662701355],"iteration":320,"passed_time":0.3379872132,"remaining_time":0.714932454},
{"learn":[4.65963044],"iteration":321,"passed_time":0.33860024,"remaining_time":0.7129533005},
{"learn":[4.654150545],"iteration":322,"passed_time":0.3393384372,"remaining_time":0.7112449597},
{"learn":[4.651394656],"iteration":323,"passed_time":0.3399639599,"remaining_time":0.7093075214},
{"learn":[4.648719352],"iteration":324,"passed_time":0.3405852627,"remaining_time":0.7073693918},
{"learn":[4.646425682],"iteration":325,"passed_time":0.3411640992,"remaining_time":0.7053515425},
{"learn":[4.642532147],"iteration":326,"passed_time":0.3417566773,"remaining_time":0.7033707762},
{"learn":[4.640105311],"iteration":327,"passed_time":0.3423833534,"remaining_time":0.7014683337},
{"learn":[4.637109406],"iteration":328,"passed_time":0.3431021094,"remaining_time":0.699761445},
{"learn":[4.632699002],"iteration":329,"passed_time":0.3437201867,"remaining_time":0.6978561366},
{"learn":[4.628197898],"iteration":330,"passed_time":0.3443155345,"remaining_time":0.6959126663},
{"learn":[4.625862476],"iteration":331,"passed_time":0.3448133662,"remaining_time":0.6937811102},
{"learn":[4.624199655],"iteration":332,"passed_time":0.345429757,"remaining_time":0.6918968407},
{"learn":[4.622012489],"iteration":333,"passed_time":0.3461311381,"remaining_time":0.6901896347},
{"learn":[4.619502542],"iteration":334,"passed_time":0.346770695,"remaining_time":0.6883657081},
{"learn":[4.614983022],"iteration":335,"passed_time":0.347393635,"remaining_time":0.6865159929},
{"learn":[4.613180069],"iteration":336,"passed_time":0.3479576117,"remaining_time":0.6845575565},
{"learn":[4.611372106],"iteration":337,"passed_time":0.3485476502,"remaining_time":0.6826584155},
{"learn":[4.607340495],"iteration":338,"passed_time":0.3491446008,"remaining_time":0.6807804752},
{"learn":[4.605522298],"iteration":339,"passed_time":0.3497605538,"remaining_time":0.6789469574},
{"learn":[4.600459756],"iteration":340,"passed_time":0.3503899088,"remaining_time":0.6771464806},
{"learn":[4.59843639],"iteration":341,"passed_time":0.351082621,"remaining_time":0.6754747503},
{"learn":[4.595198577],"iteration":342,"passed_time":0.3517284132,"remaining_time":0.6737188557},
{"learn":[4.59040982],"iteration":343,"passed_time":0.3523735868,"remaining_time":0.6719682353},
{"learn":[4.585914414],"iteration":344,"passed_time":0.3530573572,"remaining_time":0.6702973014},
{"learn":[4.582378272],"iteration":345,"passed_time":0.353595072,"remaining_time":0.6683560032},
{"learn":[4.577783837],"iteration":346,"passed_time":0.3541345388,"remaining_time":0.6664260918},
{"learn":[4.575775212],"iteration":347,"passed_time":0.3547733522,"remaining_time":0.6646903036},
{"learn":[4.571100086],"iteration":348,"passed_time":0.3555029509,"remaining_time":0.6631301463},
{"learn":[4.567155417],"iteration":349,"passed_time":0.3562534218,"remaining_time":0.6616134977},
{"learn":[4.564471197],"iteration":350,"passed_time":0.3567801011,"remaining_time":0.6596874233},
{"learn":[4.559213382],"iteration":351,"passed_time":0.3573700503,"remaining_time":0.6578857745},
{"learn":[4.558763425],"iteration":352,"passed_time":0.358024008,"remaining_time":0.6562083093},
{"learn":[4.556702883],"iteration":353,"passed_time":0.3585983203,"remaining_time":0.6543912852},
{"learn":[4.554028992],"iteration":354,"passed_time":0.3590877545,"remaining_time":0.6524270469},
{"learn":[4.549878828],"iteration":355,"passed_time":0.3598084034,"remaining_time":0.650889359},
{"learn":[4.548019787],"iteration":356,"passed_time":0.3605164657,"remaining_time":0.6493335782},
{"learn":[4.545821369],"iteration":357,"passed_time":0.3612504144,"remaining_time":0.6478289555},
{"learn":[4.542653998],"iteration":358,"passed_time":0.3619401437,"remaining_time":0.6462496716},
{"learn":[4.541758943],"iteration":359,"passed_time":0.3626010618,"remaining_time":0.6446241099},
{"learn":[4.539652276],"iteration":360,"passed_time":0.3632329647,"remaining_time":0.6429525331},
{"learn":[4.535505922],"iteration":361,"passed_time":0.3638712855,"remaining_time":0.6412980114},
{"learn":[4.532333111],"iteration":362,"passed_time":0.3645179469,"remaining_time":0.639663725},
{"learn":[4.52788391],"iteration":363,"passed_time":0.3652523591,"remaining_time":0.6381881879},
{"learn":[4.524396543],"iteration":364,"passed_time":0.3661621363,"remaining_time":0.6370217987},
{"learn":[4.521717312],"iteration":365,"passed_time":0.3666842822,"remaining_time":0.6351853412},
{"learn":[4.521229883],"iteration":366,"passed_time":0.3671436274,"remaining_time":0.633247728},
{"learn":[4.518872046],"iteration":367,"passed_time":0.3676739828,"remaining_time":0.6314401008},
{"learn":[4.518143325],"iteration":368,"passed_time":0.3683117681,"remaining_time":0.6298231047},
{"learn":[4.515699994],"iteration":369,"passed_time":0.3692042391,"remaining_time":0.6286450558},
{"learn":[4.512830722],"iteration":370,"passed_time":0.3699062541,"remaining_time":0.6271456437},
{"learn":[4.509223033],"iteration":371,"passed_time":0.3705777224,"remaining_time":0.6255989507},
{"learn":[4.507958402],"iteration":372,"passed_time":0.3712326457,"remaining_time":0.624029139},
{"learn":[4.506332673],"iteration":373,"passed_time":0.3718418368,"remaining_time":0.6223876733},
{"learn":[4.506250516],"iteration":374,"passed_time":0.3726593067,"remaining_time":0.6210988445},
{"learn":[4.502141598],"iteration":375,"passed_time":0.3734082121,"remaining_time":0.6196987349},
{"learn":[4.501586264],"iteration":376,"passed_time":0.3742083538,"remaining_time":0.6183867492},
{"learn":[4.499297193],"iteration":377,"passed_time":0.3751654944,"remaining_time":0.6173358135},
{"learn":[4.497376292],"iteration":378,"passed_time":0.3760273131,"remaining_time":0.6161291858},
{"learn":[4.496223115],"iteration":379,"passed_time":0.3766953541,"remaining_time":0.6146082094},
{"learn":[4.495917236],"iteration":380,"passed_time":0.3773698518,"remaining_time":0.6131022002},
{"learn":[4.493990588],"iteration":381,"passed_time":0.3780331591,"remaining_time":0.6115824406},
{"learn":[4.488829471],"iteration":382,"passed_time":0.3787128764,"remaining_time":0.6100935895},
{"learn":[4.485510607],"iteration":383,"passed_time":0.3792964327,"remaining_time":0.6084546941},
{"learn":[4.480968612],"iteration":384,"passed_time":0.3798721309,"remaining_time":0.6068087286},
{"learn":[4.480866349],"iteration":385,"passed_time":0.3804231351,"remaining_time":0.6051290284},
{"learn":[4.476284945],"iteration":386,"passed_time":0.3809447844,"remaining_time":0.6034086637},
{"learn":[4.473568087],"iteration":387,"passed_time":0.3814701206,"remaining_time":0.6017002933},
{"learn":[4.473462014],"iteration":388,"passed_time":0.3820008341,"remaining_time":0.6000064515},
{"learn":[4.471473217],"iteration":389,"passed_time":0.3826464723,"remaining_time":0.5984983284},
{"learn":[4.471273795],"iteration":390,"passed_time":0.3833240302,"remaining_time":0.5970443335},
{"learn":[4.470658001],"iteration":391,"passed_time":0.3841444143,"remaining_time":0.5958158262},
{"learn":[4.469629573],"iteration":392,"passed_time":0.3849211283,"remaining_time":0.5945219462},
{"learn":[4.467811877],"iteration":393,"passed_time":0.3856416163,"remaining_time":0.5931442119},
{"learn":[4.465655788],"iteration":394,"passed_time":0.3864131999,"remaining_time":0.5918480657},
{"learn":[4.463268774],"iteration":395,"passed_time":0.3871271121,"remaining_time":0.5904666053},
{"learn":[4.462676473],"iteration":396,"passed_time":0.3877706469,"remaining_time":0.5889816122},
{"learn":[4.459339705],"iteration":397,"passed_time":0.3885050983,"remaining_time":0.5876383647},
{"learn":[4.457596641],"iteration":398,"passed_time":0.3890289041,"remaining_time":0.5859808807},
{"learn":[4.456138288],"iteration":399,"passed_time":0.3895479962,"remaining_time":0.5843219943},
{"learn":[4.451700032],"iteration":400,"passed_time":0.390419463,"remaining_time":0.583195158},
{"learn":[4.449901852],"iteration":401,"passed_time":0.3911271879,"remaining_time":0.5818260158},
{"learn":[4.446356557],"iteration":402,"passed_time":0.391836259,"remaining_time":0.5804621504},
{"learn":[4.444224283],"iteration":403,"passed_time":0.3924716588,"remaining_time":0.5789928431},
{"learn":[4.439715543],"iteration":404,"passed_time":0.3932364316,"remaining_time":0.5777177204},
{"learn":[4.437435377],"iteration":405,"passed_time":0.3937249837,"remaining_time":0.576040986},
{"learn":[4.434116625],"iteration":406,"passed_time":0.394251841,"remaining_time":0.574425901},
{"learn":[4.431369496],"iteration":407,"passed_time":0.3948647551,"remaining_time":0.5729410171},
{"learn":[4.429160814],"iteration":408,"passed_time":0.3957137637,"remaining_time":0.571801551},
{"learn":[4.425986333],"iteration":409,"passed_time":0.3962821489,"remaining_time":0.5702596777},
{"learn":[4.423445333],"iteration":410,"passed_time":0.3967905075,"remaining_time":0.5686365181},
{"learn":[4.417620376],"iteration":411,"passed_time":0.3974424503,"remaining_time":0.5672236912},
{"learn":[4.417420301],"iteration":412,"passed_time":0.3979891533,"remaining_time":0.5656649709},
{"learn":[4.416278805],"iteration":413,"passed_time":0.3986369817,"remaining_time":0.5642542784},
{"learn":[4.413450784],"iteration":414,"passed_time":0.3993601946,"remaining_time":0.5629535273},
{"learn":[4.41216228],"iteration":415,"passed_time":0.4000277042,"remaining_time":0.561577354},
{"learn":[4.411033435],"iteration":416,"passed_time":0.4006712558,"remaining_time":0.5601710843},
{"learn":[4.407683188],"iteration":417,"passed_time":0.4012305239,"remaining_time":0.5586511122},
{"learn":[4.405383046],"iteration":418,"passed_time":0.401800922,"remaining_time":0.5571511592},
{"learn":[4.403497955],"iteration":419,"passed_time":0.4024608333,"remaining_time":0.555779246},
{"learn":[4.401883679],"iteration":420,"passed_time":0.4031327394,"remaining_time":0.5544272116},
{"learn":[4.398939207],"iteration":421,"passed_time":0.4037835532,"remaining_time":0.5530495112},
{"learn":[4.394810648],"iteration":422,"passed_time":0.4045069826,"remaining_time":0.5517743001},
{"learn":[4.389502563],"iteration":423,"passed_time":0.4054186971,"remaining_time":0.5507574752},
{"learn":[4.386297137],"iteration":424,"passed_time":0.4060120583,"remaining_time":0.5493104319},
{"learn":[4.384479832],"iteration":425,"passed_time":0.4065857352,"remaining_time":0.5478408732},
{"learn":[4.381824761],"iteration":426,"passed_time":0.4072249231,"remaining_time":0.5464634214},
{"learn":[4.378765936],"iteration":427,"passed_time":0.4077815028,"remaining_time":0.5449790177},
{"learn":[4.375205474],"iteration":428,"passed_time":0.4083470022,"remaining_time":0.5435108118},
{"learn":[4.369237962],"iteration":429,"passed_time":0.4089312632,"remaining_time":0.5420716745},
{"learn":[4.369073202],"iteration":430,"passed_time":0.4094945992,"remaining_time":0.5406088792},
{"learn":[4.363360309],"iteration":431,"passed_time":0.4100662531,"remaining_time":0.5391611846},
{"learn":[4.360969012],"iteration":432,"passed_time":0.4106658069,"remaining_time":0.5377540704},
{"learn":[4.357062848],"iteration":433,"passed_time":0.4114113715,"remaining_time":0.5365410973},
{"learn":[4.354159954],"iteration":434,"passed_time":0.4121624983,"remaining_time":0.5353374978},
{"learn":[4.35306654],"iteration":435,"passed_time":0.4127049001,"remaining_time":0.5338659716},
{"learn":[4.351659036],"iteration":436,"passed_time":0.4132661555,"remaining_time":0.5324229875},
{"learn":[4.346982712],"iteration":437,"passed_time":0.4139604144,"remaining_time":0.531154687},
{"learn":[4.346810154],"iteration":438,"passed_time":0.4146777506,"remaining_time":0.5299184922},
{"learn":[4.34607869],"iteration":439,"passed_time":0.415247091,"remaining_time":0.5284962977},
{"learn":[4.345119242],"iteration":440,"passed_time":0.4158483288,"remaining_time":0.5271184032},
{"learn":[4.341415968],"iteration":441,"passed_time":0.4164408985,"remaining_time":0.52573308},
{"learn":[4.33700661],"iteration":442,"passed_time":0.4170763427,"remaining_time":0.5244052435},
{"learn":[4.334791679],"iteration":443,"passed_time":0.4176570184,"remaining_time":0.523011942},
{"learn":[4.330528303],"iteration":444,"passed_time":0.4183194156,"remaining_time":0.521724215},
{"learn":[4.327057572],"iteration":445,"passed_time":0.419049022,"remaining_time":0.5205227762},
{"learn":[4.322404511],"iteration":446,"passed_time":0.419798418,"remaining_time":0.519347931},
{"learn":[4.320872581],"iteration":447,"passed_time":0.4205471272,"remaining_time":0.5181741389},
{"learn":[4.316020356],"iteration":448,"passed_time":0.4211254155,"remaining_time":0.5167931045},
{"learn":[4.312510488],"iteration":449,"passed_time":0.4216398473,"remaining_time":0.5153375912},
{"learn":[4.311689587],"iteration":450,"passed_time":0.4227619916,"remaining_time":0.5146260164},
{"learn":[4.311407236],"iteration":451,"passed_time":0.4233196394,"remaining_time":0.5132282353},
{"learn":[4.309714689],"iteration":452,"passed_time":0.4239719679,"remaining_time":0.511948491},
{"learn":[4.306234334],"iteration":453,"passed_time":0.4245827625,"remaining_time":0.5106215602},
{"learn":[4.305339864],"iteration":454,"passed_time":0.4252265134,"remaining_time":0.5093372523},
{"learn":[4.303518502],"iteration":455,"passed_time":0.4258187729,"remaining_time":0.5079943256},
{"learn":[4.299504425],"iteration":456,"passed_time":0.4265091461,"remaining_time":0.5067712611},
{"learn":[4.297029049],"iteration":457,"passed_time":0.4271188042,"remaining_time":0.5054550041},
{"learn":[4.296943249],"iteration":458,"passed_time":0.4277752494,"remaining_time":0.5041969716},
{"learn":[4.296123785],"iteration":459,"passed_time":0.4283956942,"remaining_time":0.5028992932},
{"learn":[4.294205265],"iteration":460,"passed_time":0.4290023305,"remaining_time":0.5015884081},
{"learn":[4.292050625],"iteration":461,"passed_time":0.4297668156,"remaining_time":0.5004643869},
{"learn":[4.287935591],"iteration":462,"passed_time":0.4302986252,"remaining_time":0.4990720556},
{"learn":[4.287755252],"iteration":463,"passed_time":0.4308426201,"remaining_time":0.4976975095},
{"learn":[4.286553923],"iteration":464,"passed_time":0.4314077794,"remaining_time":0.496350886},
{"learn":[4.283628762],"iteration":465,"passed_time":0.4319961327,"remaining_time":0.495034195},
{"learn":[4.283516223],"iteration":466,"passed_time":0.4324915453,"remaining_time":0.4936145474},
{"learn":[4.27988753],"iteration":467,"passed_time":0.4331377841,"remaining_time":0.4923703016},
{"learn":[4.27941115],"iteration":468,"passed_time":0.433769108,"remaining_time":0.4911117193},
{"learn":[4.276254841],"iteration":469,"passed_time":0.4343920691,"remaining_time":0.4898463758},
{"learn":[4.275263151],"iteration":470,"passed_time":0.4350850643,"remaining_time":0.4886624183},
{"learn":[4.274324646],"iteration":471,"passed_time":0.4356974401,"remaining_time":0.4873903567},
{"learn":[4.27118365],"iteration":472,"passed_time":0.4362448434,"remaining_time":0.4860486945},
{"learn":[4.267405833],"iteration":473,"passed_time":0.436809831,"remaining_time":0.4847298968},
{"learn":[4.264205024],"iteration":474,"passed_time":0.4374659565,"remaining_time":0.4835150045},
{"learn":[4.259217775],"iteration":475,"passed_time":0.4380264756,"remaining_time":0.4821972126},
{"learn":[4.255974391],"iteration":476,"passed_time":0.4385750659,"remaining_time":0.4808695167},
{"learn":[4.255765355],"iteration":477,"passed_time":0.4391061123,"remaining_time":0.4795259218},
{"learn":[4.250344669],"iteration":478,"passed_time":0.4395865607,"remaining_time":0.478130685},
{"learn":[4.2486275],"iteration":479,"passed_time":0.4401118761,"remaining_time":0.4767878657},
{"learn":[4.246702825],"iteration":480,"passed_time":0.4410029301,"remaining_time":0.4758430784},
{"learn":[4.246371235],"iteration":481,"passed_time":0.441886986,"remaining_time":0.4748909932},
{"learn":[4.244530847],"iteration":482,"passed_time":0.4426112822,"remaining_time":0.473768184},
{"learn":[4.24334846],"iteration":483,"passed_time":0.4433183287,"remaining_time":0.4726286315},
{"learn":[4.240918153],"iteration":484,"passed_time":0.4440681737,"remaining_time":0.4715363082},
{"learn":[4.237202315],"iteration":485,"passed_time":0.4448007547,"remaining_time":0.4704271356},
{"learn":[4.235873855],"iteration":486,"passed_time":0.445475683,"remaining_time":0.469258779},
{"learn":[4.235536593],"iteration":487,"passed_time":0.4461231212,"remaining_time":0.4680636025},
{"learn":[4.233988415],"iteration":488,"passed_time":0.4468811288,"remaining_time":0.4669862103},
{"learn":[4.233619625],"iteration":489,"passed_time":0.4475853204,"remaining_time":0.465854109},
{"learn":[4.233050403],"iteration":490,"passed_time":0.4482578256,"remaining_time":0.4646909027},
{"learn":[4.229436345],"iteration":491,"passed_time":0.4489908363,"remaining_time":0.4635921643},
{"learn":[4.227038412],"iteration":492,"passed_time":0.4498547152,"remaining_time":0.4626294941},
{"learn":[4.223386082],"iteration":493,"passed_time":0.450637059,"remaining_time":0.4615837082},
{"learn":[4.221442299],"iteration":494,"passed_time":0.451198801,"remaining_time":0.4603139283},
{"learn":[4.218353967],"iteration":495,"passed_time":0.4518409968,"remaining_time":0.4591287548},
{"learn":[4.217094157],"iteration":496,"passed_time":0.452357304,"remaining_time":0.4578183579},
{"learn":[4.214718595],"iteration":497,"passed_time":0.4530125178,"remaining_time":0.4566511726},
{"learn":[4.2126617],"iteration":498,"passed_time":0.4535862155,"remaining_time":0.4554041963},
{"learn":[4.212521625],"iteration":499,"passed_time":0.4543939104,"remaining_time":0.4543939104},
{"learn":[4.210574501],"iteration":500,"passed_time":0.455112903,"remaining_time":0.453296085},
{"learn":[4.20545288],"iteration":501,"passed_time":0.4556749171,"remaining_time":0.4520440413},
{"learn":[4.201868104],"iteration":502,"passed_time":0.4563110689,"remaining_time":0.4508679945},
{"learn":[4.196635572],"iteration":503,"passed_time":0.4568337822,"remaining_time":0.4495824523},
{"learn":[4.193407235],"iteration":504,"passed_time":0.4575742448,"remaining_time":0.4485133687},
{"learn":[4.191285744],"iteration":505,"passed_time":0.4582122146,"remaining_time":0.4473455218},
{"learn":[4.190394099],"iteration":506,"passed_time":0.4588631389,"remaining_time":0.4461923619},
{"learn":[4.190318776],"iteration":507,"passed_time":0.4593604331,"remaining_time":0.444892388},
{"learn":[4.188237306],"iteration":508,"passed_time":0.4601383405,"remaining_time":0.4438662577},
{"learn":[4.186246439],"iteration":509,"passed_time":0.4609856263,"remaining_time":0.4429077586},
{"learn":[4.181828706],"iteration":510,"passed_time":0.4617504748,"remaining_time":0.4418708066},
{"learn":[4.180431521],"iteration":511,"passed_time":0.4624579627,"remaining_time":0.4407802457},
{"learn":[4.176937536],"iteration":512,"passed_time":0.4631790971,"remaining_time":0.4397041331},
{"learn":[4.173029769],"iteration":513,"passed_time":0.4639901188,"remaining_time":0.4387143925},
{"learn":[4.169597542],"iteration":514,"passed_time":0.4648795908,"remaining_time":0.4377992263},
{"learn":[4.166948562],"iteration":515,"passed_time":0.4656266905,"remaining_time":0.4367506167},
{"learn":[4.165181692],"iteration":516,"passed_time":0.4663644811,"remaining_time":0.4356944765},
{"learn":[4.164117169],"iteration":517,"passed_time":0.467179501,"remaining_time":0.4347114276},
{"learn":[4.162861654],"iteration":518,"passed_time":0.4678487899,"remaining_time":0.4335939652},
{"learn":[4.162336458],"iteration":519,"passed_time":0.4686137452,"remaining_time":0.432566534},
{"learn":[4.16029277],"iteration":520,"passed_time":0.4694323212,"remaining_time":0.4315894086},
{"learn":[4.160157749],"iteration":521,"passed_time":0.4700798663,"remaining_time":0.430456276},
{"learn":[4.15533421],"iteration":522,"passed_time":0.4709052471,"remaining_time":0.4294871948},
{"learn":[4.150262426],"iteration":523,"passed_time":0.4717925389,"remaining_time":0.4285749017},
{"learn":[4.146069023],"iteration":524,"passed_time":0.4725976762,"remaining_time":0.4275883737},
{"learn":[4.142739216],"iteration":525,"passed_time":0.473405873,"remaining_time":0.4266052924},
{"learn":[4.140765158],"iteration":526,"passed_time":0.4740976276,"remaining_time":0.425518364},
{"learn":[4.139451988],"iteration":527,"passed_time":0.474861187,"remaining_time":0.4244971217},
{"learn":[4.133684419],"iteration":528,"passed_time":0.4756442396,"remaining_time":0.4234942095},
{"learn":[4.13171752],"iteration":529,"passed_time":0.476257563,"remaining_time":0.4223416125},
{"learn":[4.127852178],"iteration":530,"passed_time":0.476957401,"remaining_time":0.4212674596},
{"learn":[4.124501519],"iteration":531,"passed_time":0.477546327,"remaining_time":0.4200971448},
{"learn":[4.120723854],"iteration":532,"passed_time":0.4782250222,"remaining_time":0.4190076649},
{"learn":[4.119738303],"iteration":533,"passed_time":0.4789790672,"remaining_time":0.4179854781},
{"learn":[4.118204155],"iteration":534,"passed_time":0.4799226286,"remaining_time":0.4171290136},
{"learn":[4.114691859],"iteration":535,"passed_time":0.4806049848,"remaining_time":0.4160461062},
{"learn":[4.110535345],"iteration":536,"passed_time":0.4812406571,"remaining_time":0.4149244399},
{"learn":[4.10794655],"iteration":537,"passed_time":0.4819449911,"remaining_time":0.4138635426},
{"learn":[4.103944468],"iteration":538,"passed_time":0.4826746859,"remaining_time":0.412825659},
{"learn":[4.103708425],"iteration":539,"passed_time":0.4833470858,"remaining_time":0.4117401101},
{"learn":[4.102487672],"iteration":540,"passed_time":0.484145508,"remaining_time":0.4107630096},
{"learn":[4.098704877],"iteration":541,"passed_time":0.4848737097,"remaining_time":0.4097272307},
{"learn":[4.094628267],"iteration":542,"passed_time":0.4856037614,"remaining_time":0.4086941417},
{"learn":[4.094230943],"iteration":543,"passed_time":0.4863199482,"remaining_time":0.4076505448},
{"learn":[4.091223837],"iteration":544,"passed_time":0.4870684322,"remaining_time":0.4066351131},
{"learn":[4.091045222],"iteration":545,"passed_time":0.4878870302,"remaining_time":0.4056789592},
{"learn":[4.089502151],"iteration":546,"passed_time":0.4886687974,"remaining_time":0.4046928066},
{"learn":[4.08684339],"iteration":547,"passed_time":0.4898460027,"remaining_time":0.4040335643},
{"learn":[4.086777436],"iteration":548,"passed_time":0.4904326824,"remaining_time":0.402887322},
{"learn":[4.084363902],"iteration":549,"passed_time":0.4912144496,"remaining_time":0.4019027315},
{"learn":[4.084299787],"iteration":550,"passed_time":0.4917128764,"remaining_time":0.4006879882},
{"learn":[4.082927063],"iteration":551,"passed_time":0.4924788982,"remaining_time":0.3996930188},
{"learn":[4.079591894],"iteration":552,"passed_time":0.4932834692,"remaining_time":0.3987300375},
{"learn":[4.078377237],"iteration":553,"passed_time":0.494176218,"remaining_time":0.3978386159},
{"learn":[4.075130415],"iteration":554,"passed_time":0.4950742372,"remaining_time":0.3969514154},
{"learn":[4.073953273],"iteration":555,"passed_time":0.4957459356,"remaining_time":0.395883445},
{"learn":[4.073073787],"iteration":556,"passed_time":0.4964648849,"remaining_time":0.3948544776},
{"learn":[4.069668435],"iteration":557,"passed_time":0.4972843798,"remaining_time":0.393906265},
{"learn":[4.068820424],"iteration":558,"passed_time":0.4980862352,"remaining_time":0.392944597},
{"learn":[4.064782379],"iteration":559,"passed_time":0.4989180826,"remaining_time":0.3920070649},
{"learn":[4.061836564],"iteration":560,"passed_time":0.4997005885,"remaining_time":0.3910312983},
{"learn":[4.058525696],"iteration":561,"passed_time":0.5006281864,"remaining_time":0.3901692983},
{"learn":[4.057923887],"iteration":562,"passed_time":0.5020816692,"remaining_time":0.3897152566},
{"learn":[4.055832946],"iteration":563,"passed_time":0.5029841994,"remaining_time":0.388831757},
{"learn":[4.05567134],"iteration":564,"passed_time":0.5039503617,"remaining_time":0.3879971812},
{"learn":[4.055610463],"iteration":565,"passed_time":0.5047521459,"remaining_time":0.3870360977},
{"learn":[4.052488438],"iteration":566,"passed_time":0.505609392,"remaining_time":0.3861179308},
{"learn":[4.049339897],"iteration":567,"passed_time":0.5063634746,"remaining_time":0.3851215159},
{"learn":[4.046933791],"iteration":568,"passed_time":0.5071262061,"remaining_time":0.3841325041},
{"learn":[4.042762509],"iteration":569,"passed_time":0.5080190605,"remaining_time":0.3832424491},
{"learn":[4.042532676],"iteration":570,"passed_time":0.5088411946,"remaining_time":0.3822992513},
{"learn":[4.042082064],"iteration":571,"passed_time":0.5096604953,"remaining_time":0.3813543567},
{"learn":[4.040683092],"iteration":572,"passed_time":0.5105778432,"remaining_time":0.3804829652},
{"learn":[4.040331532],"iteration":573,"passed_time":0.5117695117,"remaining_time":0.3798150035},
{"learn":[4.03888923],"iteration":574,"passed_time":0.5130520316,"remaining_time":0.3792123711},
{"learn":[4.037220442],"iteration":575,"passed_time":0.5139304972,"remaining_time":0.3783099494},
{"learn":[4.034185805],"iteration":576,"passed_time":0.514822338,"remaining_time":0.3774174159},
{"learn":[4.031058167],"iteration":577,"passed_time":0.5156711218,"remaining_time":0.3764934488},
{"learn":[4.028837407],"iteration":578,"passed_time":0.5164128057,"remaining_time":0.3754918674},
{"learn":[4.027039008],"iteration":579,"passed_time":0.5171933956,"remaining_time":0.3745193554},
{"learn":[4.025819769],"iteration":580,"passed_time":0.5181355875,"remaining_time":0.3736640468},
{"learn":[4.022711529],"iteration":581,"passed_time":0.518896775,"remaining_time":0.3726784398},
{"learn":[4.019490942],"iteration":582,"passed_time":0.5197804183,"remaining_time":0.3717811912},
{"learn":[4.017451174],"iteration":583,"passed_time":0.5207470778,"remaining_time":0.3709431239},
{"learn":[4.015924569],"iteration":584,"passed_time":0.5215113723,"remaining_time":0.369961059},
{"learn":[4.01311427],"iteration":585,"passed_time":0.5221569233,"remaining_time":0.3688958468},
{"learn":[4.011635263],"iteration":586,"passed_time":0.5229006238,"remaining_time":0.3679011203},
{"learn":[4.01063197],"iteration":587,"passed_time":0.5238964365,"remaining_time":0.3670838977},
{"learn":[4.00494894],"iteration":588,"passed_time":0.5246358218,"remaining_time":0.3660871354},
{"learn":[4.004111118],"iteration":589,"passed_time":0.5256190446,"remaining_time":0.365260692},
{"learn":[4.000830202],"iteration":590,"passed_time":0.5265164135,"remaining_time":0.3643743031},
{"learn":[3.996402351],"iteration":591,"passed_time":0.5274358328,"remaining_time":0.3635030739},
{"learn":[3.993226024],"iteration":592,"passed_time":0.5282974822,"remaining_time":0.3625920325},
{"learn":[3.990027005],"iteration":593,"passed_time":0.5291528562,"remaining_time":0.3616768681},
{"learn":[3.988450848],"iteration":594,"passed_time":0.5298691091,"remaining_time":0.3606672087},
{"learn":[3.98654758],"iteration":595,"passed_time":0.530588499,"remaining_time":0.3596606604},
{"learn":[3.985526044],"iteration":596,"passed_time":0.5315077266,"remaining_time":0.3587899729},
{"learn":[3.982805603],"iteration":597,"passed_time":0.5323898432,"remaining_time":0.3578941755},
{"learn":[3.981605779],"iteration":598,"passed_time":0.5330860783,"remaining_time":0.3568739856},
{"learn":[3.978818527],"iteration":599,"passed_time":0.533828906,"remaining_time":0.3558859374},
{"learn":[3.976547735],"iteration":600,"passed_time":0.5346025078,"remaining_time":0.3549191358},
{"learn":[3.973860151],"iteration":601,"passed_time":0.5353312417,"remaining_time":0.3539233126},
{"learn":[3.971447833],"iteration":602,"passed_time":0.5361548172,"remaining_time":0.3529908167},
{"learn":[3.968174054],"iteration":603,"passed_time":0.536951966,"remaining_time":0.3520413552},
{"learn":[3.96602604],"iteration":604,"passed_time":0.5376881954,"remaining_time":0.3510526235},
{"learn":[3.964266397],"iteration":605,"passed_time":0.5388889742,"remaining_time":0.3503667588},
{"learn":[3.963640233],"iteration":606,"passed_time":0.5399343633,"remaining_time":0.3495785911},
{"learn":[3.960486677],"iteration":607,"passed_time":0.5409342095,"remaining_time":0.348760214},
{"learn":[3.958777256],"iteration":608,"passed_time":0.5418706547,"remaining_time":0.3479005353},
{"learn":[3.955680077],"iteration":609,"passed_time":0.5429850718,"remaining_time":0.3471543901},
{"learn":[3.955332982],"iteration":610,"passed_time":0.5443852291,"remaining_time":0.3465889593},
{"learn":[3.950739818],"iteration":611,"passed_time":0.5454568269,"remaining_time":0.3458124981},
{"learn":[3.95030508],"iteration":612,"passed_time":0.546701477,"remaining_time":0.3451443256},
{"learn":[3.948975059],"iteration":613,"passed_time":0.5476458648,"remaining_time":0.3442855111},
{"learn":[3.945969755],"iteration":614,"passed_time":0.5482966634,"remaining_time":0.3432426267},
{"learn":[3.944331806],"iteration":615,"passed_time":0.5491542057,"remaining_time":0.3423298944},
{"learn":[3.942744986],"iteration":616,"passed_time":0.5499342668,"remaining_time":0.3413692451},
{"learn":[3.939614675],"iteration":617,"passed_time":0.5508166288,"remaining_time":0.3404724145},
{"learn":[3.936978762],"iteration":618,"passed_time":0.5514264033,"remaining_time":0.3394078508},
{"learn":[3.934400663],"iteration":619,"passed_time":0.5521936121,"remaining_time":0.3384412461},
{"learn":[3.9290608],"iteration":620,"passed_time":0.5531740611,"remaining_time":0.3376054254},
{"learn":[3.92870642],"iteration":621,"passed_time":0.5544358441,"remaining_time":0.336940111},
{"learn":[3.927509585],"iteration":622,"passed_time":0.5553486266,"remaining_time":0.336061689},
{"learn":[3.927434338],"iteration":623,"passed_time":0.5563668058,"remaining_time":0.335246665},
{"learn":[3.923182595],"iteration":624,"passed_time":0.5575313447,"remaining_time":0.3345188068},
{"learn":[3.920319425],"iteration":625,"passed_time":0.5583039972,"remaining_time":0.3335554233},
{"learn":[3.9180884],"iteration":626,"passed_time":0.5590337144,"remaining_time":0.332567106},
{"learn":[3.917724691],"iteration":627,"passed_time":0.5595943067,"remaining_time":0.3314794301},
{"learn":[3.917528787],"iteration":628,"passed_time":0.5602561853,"remaining_time":0.3304531713},
{"learn":[3.916175932],"iteration":629,"passed_time":0.561002036,"remaining_time":0.3294773862},
{"learn":[3.915412439],"iteration":630,"passed_time":0.5616760831,"remaining_time":0.3284603402},
{"learn":[3.910372353],"iteration":631,"passed_time":0.5625057363,"remaining_time":0.3275349857},
{"learn":[3.909140116],"iteration":632,"passed_time":0.5631382512,"remaining_time":0.3264956369},
{"learn":[3.906226359],"iteration":633,"passed_time":0.5638841231,"remaining_time":0.3255230111},
{"learn":[3.905232801],"iteration":634,"passed_time":0.5647462791,"remaining_time":0.32461794},
{"learn":[3.903008329],"iteration":635,"passed_time":0.5655258317,"remaining_time":0.3236657276},
{"learn":[3.90173096],"iteration":636,"passed_time":0.5662176427,"remaining_time":0.322664057},
{"learn":[3.90067187],"iteration":637,"passed_time":0.5669245584,"remaining_time":0.3216719281},
{"learn":[3.899739691],"iteration":638,"passed_time":0.5685176434,"remaining_time":0.321181329},
{"learn":[3.897974816],"iteration":639,"passed_time":0.5694596212,"remaining_time":0.3203210369},
{"learn":[3.896986404],"iteration":640,"passed_time":0.5703663854,"remaining_time":0.3194407681},
{"learn":[3.895182979],"iteration":641,"passed_time":0.5711458538,"remaining_time":0.3184894325},
{"learn":[3.891453311],"iteration":642,"passed_time":0.5720220433,"remaining_time":0.317592332},
{"learn":[3.891172105],"iteration":643,"passed_time":0.5729084851,"remaining_time":0.3167009638},
{"learn":[3.890621356],"iteration":644,"passed_time":0.5736779177,"remaining_time":0.3157452105},
{"learn":[3.888549561],"iteration":645,"passed_time":0.5744166503,"remaining_time":0.3147732108},
{"learn":[3.888142006],"iteration":646,"passed_time":0.5751831723,"remaining_time":0.313817094},
{"learn":[3.885780304],"iteration":647,"passed_time":0.5759150785,"remaining_time":0.3128427587},
{"learn":[3.885728199],"iteration":648,"passed_time":0.5764970856,"remaining_time":0.3117881002},
{"learn":[3.884455107],"iteration":649,"passed_time":0.5773622247,"remaining_time":0.3108873518},
{"learn":[3.88264376],"iteration":650,"passed_time":0.5782139995,"remaining_time":0.3099795481},
{"learn":[3.881950996],"iteration":651,"passed_time":0.5790416153,"remaining_time":0.3090590217},
{"learn":[3.878287816],"iteration":652,"passed_time":0.5797278929,"remaining_time":0.3080636736},
{"learn":[3.874857954],"iteration":653,"passed_time":0.5804936594,"remaining_time":0.3071113244},
{"learn":[3.872962816],"iteration":654,"passed_time":0.5810955263,"remaining_time":0.3060732161},
{"learn":[3.868713226],"iteration":655,"passed_time":0.5818916762,"remaining_time":0.305138318},
{"learn":[3.866994294],"iteration":656,"passed_time":0.5827163254,"remaining_time":0.3042187209},
{"learn":[3.866038226],"iteration":657,"passed_time":0.5840084706,"remaining_time":0.3035423966},
{"learn":[3.86300437],"iteration":658,"passed_time":0.5853394787,"remaining_time":0.302884313},
{"learn":[3.861455807],"iteration":659,"passed_time":0.5860872272,"remaining_time":0.3019237231},
{"learn":[3.861282093],"iteration":660,"passed_time":0.5868005531,"remaining_time":0.3009461233},
{"learn":[3.85980623],"iteration":661,"passed_time":0.5876222485,"remaining_time":0.3000246526},
{"learn":[3.858601567],"iteration":662,"passed_time":0.5883548479,"remaining_time":0.2990581957},
{"learn":[3.85741886],"iteration":663,"passed_time":0.5890883208,"remaining_time":0.2980928852},
{"learn":[3.857236036],"iteration":664,"passed_time":0.5898593401,"remaining_time":0.2971471864},
{"learn":[3.855516674],"iteration":665,"passed_time":0.5906411013,"remaining_time":0.2962073991},
{"learn":[3.851442979],"iteration":666,"passed_time":0.5913947973,"remaining_time":0.2952540742},
{"learn":[3.847306626],"iteration":667,"passed_time":0.5922177474,"remaining_time":0.2943357667},
{"learn":[3.844917236],"iteration":668,"passed_time":0.5930536579,"remaining_time":0.2934241566},
{"learn":[3.844720827],"iteration":669,"passed_time":0.5937785192,"remaining_time":0.2924580766},
{"learn":[3.843465211],"iteration":670,"passed_time":0.5946543265,"remaining_time":0.2915667264},
{"learn":[3.842579146],"iteration":671,"passed_time":0.5954690687,"remaining_time":0.2906456169},
{"learn":[3.841743128],"iteration":672,"passed_time":0.5962305019,"remaining_time":0.2896989214},
{"learn":[3.839837551],"iteration":673,"passed_time":0.597108188,"remaining_time":0.2888090049},
{"learn":[3.838339643],"iteration":674,"passed_time":0.5980381206,"remaining_time":0.2879442803},
{"learn":[3.836528844],"iteration":675,"passed_time":0.599118569,"remaining_time":0.2871515035},
{"learn":[3.834865904],"iteration":676,"passed_time":0.6000260855,"remaining_time":0.2862753702},
{"learn":[3.83460642],"iteration":677,"passed_time":0.6007640033,"remaining_time":0.2853185974},
{"learn":[3.833770942],"iteration":678,"passed_time":0.6013187793,"remaining_time":0.2842758883},
{"learn":[3.831381601],"iteration":679,"passed_time":0.6019979088,"remaining_time":0.2832931335},
{"learn":[3.829147097],"iteration":680,"passed_time":0.6025631296,"remaining_time":0.2822579124},
{"learn":[3.826448614],"iteration":681,"passed_time":0.6031102076,"remaining_time":0.28121561},
{"learn":[3.823566585],"iteration":682,"passed_time":0.6037426364,"remaining_time":0.2802143715},
{"learn":[3.820778434],"iteration":683,"passed_time":0.6042864897,"remaining_time":0.2791732906},
{"learn":[3.82064589],"iteration":684,"passed_time":0.6048017499,"remaining_time":0.2781205127},
{"learn":[3.818921386],"iteration":685,"passed_time":0.605369546,"remaining_time":0.2770933491},
{"learn":[3.816234217],"iteration":686,"passed_time":0.6059374342,"remaining_time":0.2760675646},
{"learn":[3.814141038],"iteration":687,"passed_time":0.6064950975,"remaining_time":0.2750384745},
{"learn":[3.81291813],"iteration":688,"passed_time":0.6071001923,"remaining_time":0.2740321623},
{"learn":[3.810517677],"iteration":689,"passed_time":0.6076953128,"remaining_time":0.2730225318},
{"learn":[3.807964393],"iteration":690,"passed_time":0.6082805022,"remaining_time":0.2720096602},
{"learn":[3.805956553],"iteration":691,"passed_time":0.6088376077,"remaining_time":0.2709855248},
{"learn":[3.803953142],"iteration":692,"passed_time":0.6093541026,"remaining_time":0.2699447467},
{"learn":[3.802578145],"iteration":693,"passed_time":0.609916589,"remaining_time":0.2689257582},
{"learn":[3.801254999],"iteration":694,"passed_time":0.6104424982,"remaining_time":0.2678920316},
{"learn":[3.79817624],"iteration":695,"passed_time":0.6110971858,"remaining_time":0.2669160122},
{"learn":[3.796397875],"iteration":696,"passed_time":0.6120604497,"remaining_time":0.2660750592},
{"learn":[3.794575091],"iteration":697,"passed_time":0.6131249165,"remaining_time":0.2652775427},
{"learn":[3.793578721],"iteration":698,"passed_time":0.6144457739,"remaining_time":0.264589668},
{"learn":[3.790655765],"iteration":699,"passed_time":0.6153370136,"remaining_time":0.263715863},
{"learn":[3.78933031],"iteration":700,"passed_time":0.6159518773,"remaining_time":0.2627241246},
{"learn":[3.785787167],"iteration":701,"passed_time":0.6165434058,"remaining_time":0.261723554},
{"learn":[3.78409076],"iteration":702,"passed_time":0.6171476293,"remaining_time":0.2607295105},
{"learn":[3.781670344],"iteration":703,"passed_time":0.617755569,"remaining_time":0.259738137},
{"learn":[3.781658578],"iteration":704,"passed_time":0.6180732711,"remaining_time":0.2586264042},
{"learn":[3.779389839],"iteration":705,"passed_time":0.6185901249,"remaining_time":0.2575998537},
{"learn":[3.77852865],"iteration":706,"passed_time":0.619137407,"remaining_time":0.2565873554},
{"learn":[3.777739713],"iteration":707,"passed_time":0.6197289786,"remaining_time":0.2555944375},
{"learn":[3.776349868],"iteration":708,"passed_time":0.6203117077,"remaining_time":0.2545990225},
{"learn":[3.772115976],"iteration":709,"passed_time":0.6209286136,"remaining_time":0.2536187295},
{"learn":[3.768879655],"iteration":710,"passed_time":0.6214568188,"remaining_time":0.2526034045},
{"learn":[3.76633811],"iteration":711,"passed_time":0.621979312,"remaining_time":0.2515871375},
{"learn":[3.766198581],"iteration":712,"passed_time":0.6225297944,"remaining_time":0.2505835217},
{"learn":[3.765024878],"iteration":713,"passed_time":0.6230262715,"remaining_time":0.2495595429},
{"learn":[3.763923667],"iteration":714,"passed_time":0.6236074326,"remaining_time":0.2485707948},
{"learn":[3.762719637],"iteration":715,"passed_time":0.6241866497,"remaining_time":0.2475824141},
{"learn":[3.761432238],"iteration":716,"passed_time":0.6247379865,"remaining_time":0.2465841704},
{"learn":[3.759024581],"iteration":717,"passed_time":0.6253876525,"remaining_time":0.2456257911},
{"learn":[3.758382073],"iteration":718,"passed_time":0.6259881708,"remaining_time":0.2446490626},
{"learn":[3.756377147],"iteration":719,"passed_time":0.6265459209,"remaining_time":0.243656747},
{"learn":[3.755440069],"iteration":720,"passed_time":0.6270750805,"remaining_time":0.2426545735},
{"learn":[3.754474977],"iteration":721,"passed_time":0.6279886218,"remaining_time":0.2418017131},
{"learn":[3.752030933],"iteration":722,"passed_time":0.6291294077,"remaining_time":0.2410357482},
{"learn":[3.748468793],"iteration":723,"passed_time":0.6301615686,"remaining_time":0.2402273383},
{"learn":[3.746945228],"iteration":724,"passed_time":0.630831302,"remaining_time":0.2392808387},
{"learn":[3.743370239],"iteration":725,"passed_time":0.6314126081,"remaining_time":0.2383017281},
{"learn":[3.739374324],"iteration":726,"passed_time":0.6320699833,"remaining_time":0.2373522771},
{"learn":[3.736288514],"iteration":727,"passed_time":0.6326449032,"remaining_time":0.236372821},
{"learn":[3.733960515],"iteration":728,"passed_time":0.6331972956,"remaining_time":0.2353861003},
{"learn":[3.733604902],"iteration":729,"passed_time":0.6338350989,"remaining_time":0.2344321599},
{"learn":[3.732639665],"iteration":730,"passed_time":0.634398114,"remaining_time":0.2334515632},
{"learn":[3.731455385],"iteration":731,"passed_time":0.6349128252,"remaining_time":0.2324544223},
{"learn":[3.728120685],"iteration":732,"passed_time":0.6354829864,"remaining_time":0.2314787959},
{"learn":[3.726065096],"iteration":733,"passed_time":0.6360533597,"remaining_time":0.2305043511},
{"learn":[3.723945593],"iteration":734,"passed_time":0.6366225248,"remaining_time":0.2295305702},
{"learn":[3.722771011],"iteration":735,"passed_time":0.6371874152,"remaining_time":0.2285563554},
{"learn":[3.720456039],"iteration":736,"passed_time":0.6377145882,"remaining_time":0.227569792},
{"learn":[3.719731213],"iteration":737,"passed_time":0.6383128806,"remaining_time":0.2266097218},
{"learn":[3.717181838],"iteration":738,"passed_time":0.6389023805,"remaining_time":0.2256475254},
{"learn":[3.714564069],"iteration":739,"passed_time":0.6396970765,"remaining_time":0.2247584323},
{"learn":[3.71363855],"iteration":740,"passed_time":0.640346927,"remaining_time":0.2238189664},
{"learn":[3.710517808],"iteration":741,"passed_time":0.6409516797,"remaining_time":0.2228646002},
{"learn":[3.708355845],"iteration":742,"passed_time":0.6414831551,"remaining_time":0.2218858289},
{"learn":[3.70656784],"iteration":743,"passed_time":0.6420457484,"remaining_time":0.2209189672},
{"learn":[3.702710163],"iteration":744,"passed_time":0.6427893457,"remaining_time":0.2200151452},
{"learn":[3.70262089],"iteration":745,"passed_time":0.6438319575,"remaining_time":0.2192135619},
{"learn":[3.699892446],"iteration":746,"passed_time":0.6447046689,"remaining_time":0.2183537901},
{"learn":[3.69786148],"iteration":747,"passed_time":0.6455011905,"remaining_time":0.2174683155},
{"learn":[3.693072269],"iteration":748,"passed_time":0.6464256978,"remaining_time":0.2166259682},
{"learn":[3.691410987],"iteration":749,"passed_time":0.6474010213,"remaining_time":0.2158003404},
{"learn":[3.687632467],"iteration":750,"passed_time":0.6485144155,"remaining_time":0.2150200925},
{"learn":[3.687370328],"iteration":751,"passed_time":0.6491476846,"remaining_time":0.2140806194},
{"learn":[3.686233416],"iteration":752,"passed_time":0.6498072089,"remaining_time":0.2131505718},
{"learn":[3.685436595],"iteration":753,"passed_time":0.650442517,"remaining_time":0.2122133411},
{"learn":[3.681545532],"iteration":754,"passed_time":0.6511071461,"remaining_time":0.2112864249},
{"learn":[3.680739555],"iteration":755,"passed_time":0.6517599156,"remaining_time":0.2103563749},
{"learn":[3.680577289],"iteration":756,"passed_time":0.6523159358,"remaining_time":0.2093960005},
{"learn":[3.678491393],"iteration":757,"passed_time":0.6528918081,"remaining_time":0.2084430311},
{"learn":[3.676535358],"iteration":758,"passed_time":0.6534766922,"remaining_time":0.2074939168},
{"learn":[3.675946908],"iteration":759,"passed_time":0.654110546,"remaining_time":0.2065612251},
{"learn":[3.675656893],"iteration":760,"passed_time":0.6547090725,"remaining_time":0.2056182238},
{"learn":[3.674531808],"iteration":761,"passed_time":0.6552817721,"remaining_time":0.2046680601},
{"learn":[3.673484006],"iteration":762,"passed_time":0.6558321853,"remaining_time":0.2037119632},
{"learn":[3.669845987],"iteration":763,"passed_time":0.6563930657,"remaining_time":0.2027601617},
{"learn":[3.669770257],"iteration":764,"passed_time":0.6569612052,"remaining_time":0.201811612},
{"learn":[3.668435575],"iteration":765,"passed_time":0.6576787406,"remaining_time":0.2009096936},
{"learn":[3.666572155],"iteration":766,"passed_time":0.6587159659,"remaining_time":0.2001053717},
{"learn":[3.66543892],"iteration":767,"passed_time":0.6596264698,"remaining_time":0.1992621628},
{"learn":[3.665143651],"iteration":768,"passed_time":0.6602506975,"remaining_time":0.1983327843},
{"learn":[3.664105594],"iteration":769,"passed_time":0.660906428,"remaining_time":0.1974136084},
{"learn":[3.661846175],"iteration":770,"passed_time":0.6615007334,"remaining_time":0.1964768715},
{"learn":[3.658321112],"iteration":771,"passed_time":0.6621278052,"remaining_time":0.195550699},
{"learn":[3.658008711],"iteration":772,"passed_time":0.6627169617,"remaining_time":0.194614166},
{"learn":[3.656933526],"iteration":773,"passed_time":0.6632806783,"remaining_time":0.1936711025},
{"learn":[3.656503288],"iteration":774,"passed_time":0.6638613897,"remaining_time":0.1927339518},
{"learn":[3.653456547],"iteration":775,"passed_time":0.6644963776,"remaining_time":0.1918133874},
{"learn":[3.65155751],"iteration":776,"passed_time":0.6650516679,"remaining_time":0.1908706846},
{"learn":[3.65106216],"iteration":777,"passed_time":0.6656242606,"remaining_time":0.189933915},
{"learn":[3.650378423],"iteration":778,"passed_time":0.6662187512,"remaining_time":0.1890042927},
{"learn":[3.649393887],"iteration":779,"passed_time":0.6668559102,"remaining_time":0.1880875644},
{"learn":[3.64902744],"iteration":780,"passed_time":0.6673936198,"remaining_time":0.1871436655},
{"learn":[3.648174921],"iteration":781,"passed_time":0.6680051264,"remaining_time":0.1862213779},
{"learn":[3.647438234],"iteration":782,"passed_time":0.6687646435,"remaining_time":0.1853409038},
{"learn":[3.645609522],"iteration":783,"passed_time":0.6694855914,"remaining_time":0.1844501119},
{"learn":[3.643271735],"iteration":784,"passed_time":0.6700383308,"remaining_time":0.183513683},
{"learn":[3.641495355],"iteration":785,"passed_time":0.670619502,"remaining_time":0.1825859713},
{"learn":[3.637317859],"iteration":786,"passed_time":0.6712013595,"remaining_time":0.181659326},
{"learn":[3.635771177],"iteration":787,"passed_time":0.671773157,"remaining_time":0.1807308494},
{"learn":[3.632674606],"iteration":788,"passed_time":0.6724032559,"remaining_time":0.1798188682},
{"learn":[3.631570628],"iteration":789,"passed_time":0.6731458511,"remaining_time":0.1789375047},
{"learn":[3.63064265],"iteration":790,"passed_time":0.6738861905,"remaining_time":0.1780558961},
{"learn":[3.629036297],"iteration":791,"passed_time":0.6745441876,"remaining_time":0.177153019},
{"learn":[3.627035492],"iteration":792,"passed_time":0.675122333,"remaining_time":0.1762299154},
{"learn":[3.624136744],"iteration":793,"passed_time":0.6756945536,"remaining_time":0.1753061436},
{"learn":[3.624002035],"iteration":794,"passed_time":0.6763281829,"remaining_time":0.1743990912},
{"learn":[3.623453793],"iteration":795,"passed_time":0.6769213121,"remaining_time":0.1734823463},
{"learn":[3.620907529],"iteration":796,"passed_time":0.6774703994,"remaining_time":0.1725551958},
{"learn":[3.620226488],"iteration":797,"passed_time":0.678050376,"remaining_time":0.171636812},
{"learn":[3.619571036],"iteration":798,"passed_time":0.6785914532,"remaining_time":0.1707094895},
{"learn":[3.616097229],"iteration":799,"passed_time":0.6792507813,"remaining_time":0.1698126953},
{"learn":[3.615290085],"iteration":800,"passed_time":0.6798351516,"remaining_time":0.1688978716},
{"learn":[3.612721679],"iteration":801,"passed_time":0.6803330998,"remaining_time":0.1679625359},
{"learn":[3.610551685],"iteration":802,"passed_time":0.6809026999,"remaining_time":0.1670458678},
{"learn":[3.607586976],"iteration":803,"passed_time":0.6814774188,"remaining_time":0.1661313111},
{"learn":[3.606534224],"iteration":804,"passed_time":0.6820349997,"remaining_time":0.1652134471},
{"learn":[3.604325523],"iteration":805,"passed_time":0.6826831903,"remaining_time":0.1643182865},
{"learn":[3.604134381],"iteration":806,"passed_time":0.6833431672,"remaining_time":0.1634265567},
{"learn":[3.603246042],"iteration":807,"passed_time":0.6839204385,"remaining_time":0.1625157478},
{"learn":[3.599576518],"iteration":808,"passed_time":0.6846653856,"remaining_time":0.1616453506},
{"learn":[3.596992363],"iteration":809,"passed_time":0.6852836694,"remaining_time":0.1607455521},
{"learn":[3.594569359],"iteration":810,"passed_time":0.6859176289,"remaining_time":0.1598501009},
{"learn":[3.593563841],"iteration":811,"passed_time":0.6864680801,"remaining_time":0.1589359594},
{"learn":[3.593070667],"iteration":812,"passed_time":0.6870339549,"remaining_time":0.1580262602},
{"learn":[3.592853887],"iteration":813,"passed_time":0.687587798,"remaining_time":0.1571146565},
{"learn":[3.592111771],"iteration":814,"passed_time":0.6883588702,"remaining_time":0.1562532405},
{"learn":[3.591632559],"iteration":815,"passed_time":0.6889849632,"remaining_time":0.1553593544},
{"learn":[3.588943748],"iteration":816,"passed_time":0.6895323801,"remaining_time":0.1544485013},
{"learn":[3.585729102],"iteration":817,"passed_time":0.6901020819,"remaining_time":0.153543495},
{"learn":[3.585351024],"iteration":818,"passed_time":0.6906502712,"remaining_time":0.1526345532},
{"learn":[3.583829815],"iteration":819,"passed_time":0.6911958093,"remaining_time":0.1517259094},
{"learn":[3.582659943],"iteration":820,"passed_time":0.6917716623,"remaining_time":0.1508247595},
{"learn":[3.581498929],"iteration":821,"passed_time":0.6923724731,"remaining_time":0.1499298056},
{"learn":[3.579377806],"iteration":822,"passed_time":0.6929656495,"remaining_time":0.1490339246},
{"learn":[3.577267441],"iteration":823,"passed_time":0.6935195615,"remaining_time":0.1481303918},
{"learn":[3.574046704],"iteration":824,"passed_time":0.6940823184,"remaining_time":0.1472295827},
{"learn":[3.571978694],"iteration":825,"passed_time":0.6946460086,"remaining_time":0.1463297887},
{"learn":[3.570638988],"iteration":826,"passed_time":0.6952147271,"remaining_time":0.1454318595},
{"learn":[3.568403621],"iteration":827,"passed_time":0.6958040553,"remaining_time":0.1445390067},
{"learn":[3.565271875],"iteration":828,"passed_time":0.6963617762,"remaining_time":0.1436403664},
{"learn":[3.563361176],"iteration":829,"passed_time":0.6969291445,"remaining_time":0.1427445236},
{"learn":[3.562784378],"iteration":830,"passed_time":0.6977580246,"remaining_time":0.1419026548},
{"learn":[3.560021818],"iteration":831,"passed_time":0.698404147,"remaining_time":0.1410239143},
{"learn":[3.559930153],"iteration":832,"passed_time":0.6989641958,"remaining_time":0.1401284762},
{"learn":[3.559636879],"iteration":833,"passed_time":0.6995378355,"remaining_time":0.1392365476},
{"learn":[3.556518296],"iteration":834,"passed_time":0.7001043178,"remaining_time":0.138343967},
{"learn":[3.555017184],"iteration":835,"passed_time":0.7007178877,"remaining_time":0.1374614038},
{"learn":[3.55451248],"iteration":836,"passed_time":0.7012796674,"remaining_time":0.1365693976},
{"learn":[3.552065828],"iteration":837,"passed_time":0.7018678582,"remaining_time":0.1356832852},
{"learn":[3.55083415],"iteration":838,"passed_time":0.7024438786,"remaining_time":0.1347955476},
{"learn":[3.548420043],"iteration":839,"passed_time":0.7030571884,"remaining_time":0.1339156549},
{"learn":[3.545319327],"iteration":840,"passed_time":0.70387748,"remaining_time":0.1330755283},
{"learn":[3.544416303],"iteration":841,"passed_time":0.7045710242,"remaining_time":0.1322116649},
{"learn":[3.541570491],"iteration":842,"passed_time":0.705135592,"remaining_time":0.131324185},
{"learn":[3.540789265],"iteration":843,"passed_time":0.7058010207,"remaining_time":0.1304561128},
{"learn":[3.540502777],"iteration":844,"passed_time":0.7064503422,"remaining_time":0.1295855657},
{"learn":[3.539863534],"iteration":845,"passed_time":0.7070117296,"remaining_time":0.1286995347},
{"learn":[3.539404261],"iteration":846,"passed_time":0.7075518488,"remaining_time":0.1278104284},
{"learn":[3.538042081],"iteration":847,"passed_time":0.7081297484,"remaining_time":0.1269289172},
{"learn":[3.537043296],"iteration":848,"passed_time":0.7087056715,"remaining_time":0.1260477696},
{"learn":[3.53567564],"iteration":849,"passed_time":0.7093676313,"remaining_time":0.1251825232},
{"learn":[3.53565107],"iteration":850,"passed_time":0.7095998389,"remaining_time":0.12424251},
{"learn":[3.535600016],"iteration":851,"passed_time":0.7101501796,"remaining_time":0.1233594209},
{"learn":[3.533444905],"iteration":852,"passed_time":0.7107356044,"remaining_time":0.1224831581},
{"learn":[3.5312637],"iteration":853,"passed_time":0.7113630592,"remaining_time":0.1216147619},
{"learn":[3.530456983],"iteration":854,"passed_time":0.7119832303,"remaining_time":0.120745694},
{"learn":[3.527596328],"iteration":855,"passed_time":0.7125941458,"remaining_time":0.1198756507},
{"learn":[3.525984144],"iteration":856,"passed_time":0.7132217531,"remaining_time":0.1190089973},
{"learn":[3.524544886],"iteration":857,"passed_time":0.7138627387,"remaining_time":0.1181451153},
{"learn":[3.52281088],"iteration":858,"passed_time":0.7144548086,"remaining_time":0.1172737229},
{"learn":[3.522424737],"iteration":859,"passed_time":0.7149739154,"remaining_time":0.1163911025},
{"learn":[3.519857555],"iteration":860,"passed_time":0.7155786957,"remaining_time":0.1155231576},
{"learn":[3.518700112],"iteration":861,"passed_time":0.7162850551,"remaining_time":0.1146720854},
{"learn":[3.517315639],"iteration":862,"passed_time":0.7169817212,"remaining_time":0.1138198097},
{"learn":[3.516344317],"iteration":863,"passed_time":0.71756651,"remaining_time":0.112950284},
{"learn":[3.512515442],"iteration":864,"passed_time":0.7181363103,"remaining_time":0.1120790773},
{"learn":[3.511969807],"iteration":865,"passed_time":0.718901396,"remaining_time":0.1112387841},
{"learn":[3.509504856],"iteration":866,"passed_time":0.719819369,"remaining_time":0.1104221177},
{"learn":[3.507407687],"iteration":867,"passed_time":0.7205373975,"remaining_time":0.1095748116},
{"learn":[3.504826981],"iteration":868,"passed_time":0.7211426428,"remaining_time":0.1087108012},
{"learn":[3.504291322],"iteration":869,"passed_time":0.7217472441,"remaining_time":0.1078472893},
{"learn":[3.503950992],"iteration":870,"passed_time":0.7223212715,"remaining_time":0.1069798439},
{"learn":[3.502989723],"iteration":871,"passed_time":0.7229380882,"remaining_time":0.1061193524},
{"learn":[3.49933438],"iteration":872,"passed_time":0.7235264167,"remaining_time":0.1052552748},
{"learn":[3.495631366],"iteration":873,"passed_time":0.7240941067,"remaining_time":0.1043888529},
{"learn":[3.494206287],"iteration":874,"passed_time":0.724684399,"remaining_time":0.1035263427},
{"learn":[3.493227817],"iteration":875,"passed_time":0.7252553085,"remaining_time":0.1026617103},
{"learn":[3.491458914],"iteration":876,"passed_time":0.7258281622,"remaining_time":0.1017980205},
{"learn":[3.491375987],"iteration":877,"passed_time":0.7264041905,"remaining_time":0.1009354342},
{"learn":[3.489063536],"iteration":878,"passed_time":0.7271542308,"remaining_time":0.1000974538},
{"learn":[3.487078208],"iteration":879,"passed_time":0.7278296325,"remaining_time":0.09924949535},
{"learn":[3.486690041],"iteration":880,"passed_time":0.7284218877,"remaining_time":0.09839069766},
{"learn":[3.485607223],"iteration":881,"passed_time":0.7290088788,"remaining_time":0.09753180011},
{"learn":[3.484064047],"iteration":882,"passed_time":0.7295912077,"remaining_time":0.09667290068},
{"learn":[3.481188348],"iteration":883,"passed_time":0.7301737631,"remaining_time":0.0958146567},
{"learn":[3.481109987],"iteration":884,"passed_time":0.7307318182,"remaining_time":0.09495385209},
{"learn":[3.477015121],"iteration":885,"passed_time":0.7313250122,"remaining_time":0.09409825214},
{"learn":[3.476563938],"iteration":886,"passed_time":0.7318958393,"remaining_time":0.09324039441},
{"learn":[3.475425116],"iteration":887,"passed_time":0.732507971,"remaining_time":0.09238839274},
{"learn":[3.473719879],"iteration":888,"passed_time":0.733120755,"remaining_time":0.09153701215},
{"learn":[3.473034217],"iteration":889,"passed_time":0.734085395,"remaining_time":0.09072965557},
{"learn":[3.471856965],"iteration":890,"passed_time":0.7352391814,"remaining_time":0.08994508504},
{"learn":[3.469941185],"iteration":891,"passed_time":0.7361347354,"remaining_time":0.08912842088},
{"learn":[3.468107831],"iteration":892,"passed_time":0.7370310459,"remaining_time":0.08831167067},
{"learn":[3.465745037],"iteration":893,"passed_time":0.7377203233,"remaining_time":0.08747019493},
{"learn":[3.465564569],"iteration":894,"passed_time":0.7383421243,"remaining_time":0.08662114308},
{"learn":[3.464627796],"iteration":895,"passed_time":0.738921832,"remaining_time":0.08576771264},
{"learn":[3.462993764],"iteration":896,"passed_time":0.7395186881,"remaining_time":0.08491686162},
{"learn":[3.46214422],"iteration":897,"passed_time":0.7401186909,"remaining_time":0.08406693371},
{"learn":[3.46144144],"iteration":898,"passed_time":0.7407044822,"remaining_time":0.08321596519},
{"learn":[3.460596715],"iteration":899,"passed_time":0.741281814,"remaining_time":0.082364646},
{"learn":[3.460138149],"iteration":900,"passed_time":0.7418550162,"remaining_time":0.08151348125},
{"learn":[3.459720411],"iteration":901,"passed_time":0.7424408796,"remaining_time":0.08066430842},
{"learn":[3.458619732],"iteration":902,"passed_time":0.743021426,"remaining_time":0.07981514765},
{"learn":[3.456917653],"iteration":903,"passed_time":0.7436927762,"remaining_time":0.07897622403},
{"learn":[3.454221666],"iteration":904,"passed_time":0.7443240873,"remaining_time":0.07813346773},
{"learn":[3.452294969],"iteration":905,"passed_time":0.7449210475,"remaining_time":0.0772876142},
{"learn":[3.451817804],"iteration":906,"passed_time":0.7455007828,"remaining_time":0.07644054333},
{"learn":[3.451700292],"iteration":907,"passed_time":0.7460793851,"remaining_time":0.07559394651},
{"learn":[3.449719614],"iteration":908,"passed_time":0.7466761212,"remaining_time":0.0747497547},
{"learn":[3.448260272],"iteration":909,"passed_time":0.7473232792,"remaining_time":0.07391109355},
{"learn":[3.446396135],"iteration":910,"passed_time":0.7478905151,"remaining_time":0.07306504483},
{"learn":[3.444159704],"iteration":911,"passed_time":0.7484732334,"remaining_time":0.07222110146},
{"learn":[3.443464496],"iteration":912,"passed_time":0.7493301513,"remaining_time":0.07140385889},
{"learn":[3.442761136],"iteration":913,"passed_time":0.750063088,"remaining_time":0.07057486386},
{"learn":[3.441273526],"iteration":914,"passed_time":0.7507408445,"remaining_time":0.06974095276},
{"learn":[3.439572383],"iteration":915,"passed_time":0.7513389371,"remaining_time":0.06890007721},
{"learn":[3.437368425],"iteration":916,"passed_time":0.7519026461,"remaining_time":0.06805661901},
{"learn":[3.435199942],"iteration":917,"passed_time":0.7525145505,"remaining_time":0.06721807532},
{"learn":[3.431789033],"iteration":918,"passed_time":0.753073015,"remaining_time":0.06637531471},
{"learn":[3.428883213],"iteration":919,"passed_time":0.753651352,"remaining_time":0.06553490018},
{"learn":[3.426599805],"iteration":920,"passed_time":0.7542962787,"remaining_time":0.06470076657},
{"learn":[3.424810705],"iteration":921,"passed_time":0.7549130165,"remaining_time":0.06386465866},
{"learn":[3.421586997],"iteration":922,"passed_time":0.7554824161,"remaining_time":0.06302507697},
{"learn":[3.42095403],"iteration":923,"passed_time":0.7561222608,"remaining_time":0.06219187427},
{"learn":[3.417316907],"iteration":924,"passed_time":0.7567379549,"remaining_time":0.06135713148},
{"learn":[3.415001978],"iteration":925,"passed_time":0.7572642288,"remaining_time":0.06051571591},
{"learn":[3.413271191],"iteration":926,"passed_time":0.7578405112,"remaining_time":0.05967891836},
{"learn":[3.412319338],"iteration":927,"passed_time":0.7584168357,"remaining_time":0.05884268553},
{"learn":[3.411832998],"iteration":928,"passed_time":0.7589417237,"remaining_time":0.05800308115},
{"learn":[3.411579108],"iteration":929,"passed_time":0.7594763026,"remaining_time":0.05716488299},
{"learn":[3.410263302],"iteration":930,"passed_time":0.7600358321,"remaining_time":0.05632918626},
{"learn":[3.40897256],"iteration":931,"passed_time":0.7606025629,"remaining_time":0.05549460759},
{"learn":[3.408121694],"iteration":932,"passed_time":0.7611864381,"remaining_time":0.05466183425},
{"learn":[3.407099154],"iteration":933,"passed_time":0.7616917141,"remaining_time":0.05382403975},
{"learn":[3.406496377],"iteration":934,"passed_time":0.7623996486,"remaining_time":0.05300104509},
{"learn":[3.405451974],"iteration":935,"passed_time":0.7630907541,"remaining_time":0.05217714558},
{"learn":[3.403556717],"iteration":936,"passed_time":0.7636942165,"remaining_time":0.05134763676},
{"learn":[3.403459617],"iteration":937,"passed_time":0.7645932707,"remaining_time":0.05053814795},
{"learn":[3.402025462],"iteration":938,"passed_time":0.7652020287,"remaining_time":0.04970960996},
{"learn":[3.399730873],"iteration":939,"passed_time":0.765773106,"remaining_time":0.04887913442},
{"learn":[3.399120383],"iteration":940,"passed_time":0.7662699516,"remaining_time":0.04804455595},
{"learn":[3.398658494],"iteration":941,"passed_time":0.766817036,"remaining_time":0.04721378778},
{"learn":[3.396402292],"iteration":942,"passed_time":0.7674311654,"remaining_time":0.04638767384},
{"learn":[3.395990223],"iteration":943,"passed_time":0.767962879,"remaining_time":0.04555711994},
{"learn":[3.393956141],"iteration":944,"passed_time":0.7685409747,"remaining_time":0.044729898},
{"learn":[3.390384728],"iteration":945,"passed_time":0.7691285721,"remaining_time":0.04390374513},
{"learn":[3.388451565],"iteration":946,"passed_time":0.769668359,"remaining_time":0.04307542031},
{"learn":[3.386603466],"iteration":947,"passed_time":0.7702583051,"remaining_time":0.04225045556},
{"learn":[3.383715775],"iteration":948,"passed_time":0.7708240647,"remaining_time":0.0414246863},
{"learn":[3.382399702],"iteration":949,"passed_time":0.7713995412,"remaining_time":0.04059997585},
{"learn":[3.382343989],"iteration":950,"passed_time":0.7720075225,"remaining_time":0.03977746435},
{"learn":[3.38045172],"iteration":951,"passed_time":0.7725857555,"remaining_time":0.03895390364},
{"learn":[3.378421269],"iteration":952,"passed_time":0.7731846057,"remaining_time":0.03813187457},
{"learn":[3.373715543],"iteration":953,"passed_time":0.7738433784,"remaining_time":0.03731320273},
{"learn":[3.372358334],"iteration":954,"passed_time":0.7743872665,"remaining_time":0.03648945235},
{"learn":[3.370625043],"iteration":955,"passed_time":0.7749668237,"remaining_time":0.03566792913},
{"learn":[3.368906156],"iteration":956,"passed_time":0.7755093828,"remaining_time":0.03484524917},
{"learn":[3.366825424],"iteration":957,"passed_time":0.7760147908,"remaining_time":0.03402152528},
{"learn":[3.365617021],"iteration":958,"passed_time":0.7767036505,"remaining_time":0.03320630831},
{"learn":[3.363870384],"iteration":959,"passed_time":0.7773072782,"remaining_time":0.03238780326},
{"learn":[3.36071105],"iteration":960,"passed_time":0.7779002008,"remaining_time":0.03156931096},
{"learn":[3.358104346],"iteration":961,"passed_time":0.7784799241,"remaining_time":0.03075076623},
{"learn":[3.357360672],"iteration":962,"passed_time":0.7790827574,"remaining_time":0.02993360543},
{"learn":[3.356377284],"iteration":963,"passed_time":0.7797750422,"remaining_time":0.02912022979},
{"learn":[3.355132081],"iteration":964,"passed_time":0.7806002854,"remaining_time":0.02831192745},
{"learn":[3.353967233],"iteration":965,"passed_time":0.7811857129,"remaining_time":0.02749514932},
{"learn":[3.351729575],"iteration":966,"passed_time":0.7817473437,"remaining_time":0.02667803758},
{"learn":[3.351330833],"iteration":967,"passed_time":0.7823377792,"remaining_time":0.02586240593},
{"learn":[3.349073503],"iteration":968,"passed_time":0.7829207468,"remaining_time":0.02504700016},
{"learn":[3.346973719],"iteration":969,"passed_time":0.7835191965,"remaining_time":0.02423255247},
{"learn":[3.345752287],"iteration":970,"passed_time":0.7841405961,"remaining_time":0.02341923511},
{"learn":[3.342951965],"iteration":971,"passed_time":0.7847097893,"remaining_time":0.02260480874},
{"learn":[3.342123015],"iteration":972,"passed_time":0.7852572782,"remaining_time":0.02179028419},
{"learn":[3.340956238],"iteration":973,"passed_time":0.7858608827,"remaining_time":0.0209778059},
{"learn":[3.340720114],"iteration":974,"passed_time":0.7864273854,"remaining_time":0.02016480475},
{"learn":[3.338976313],"iteration":975,"passed_time":0.7870891791,"remaining_time":0.01935465195},
{"learn":[3.337312641],"iteration":976,"passed_time":0.787681153,"remaining_time":0.01854315918},
{"learn":[3.335894303],"iteration":977,"passed_time":0.7882657013,"remaining_time":0.01773194829},
{"learn":[3.335804332],"iteration":978,"passed_time":0.7888305,"remaining_time":0.01692077681},
{"learn":[3.332533756],"iteration":979,"passed_time":0.7893906369,"remaining_time":0.016110013},
{"learn":[3.331048125],"iteration":980,"passed_time":0.7899188072,"remaining_time":0.01529914102},
{"learn":[3.329541834],"iteration":981,"passed_time":0.7905181293,"remaining_time":0.01449014901},
{"learn":[3.326283726],"iteration":982,"passed_time":0.7912999765,"remaining_time":0.01368474018},
{"learn":[3.323443325],"iteration":983,"passed_time":0.7918757951,"remaining_time":0.01287602919},
{"learn":[3.32296893],"iteration":984,"passed_time":0.7925232578,"remaining_time":0.0120688821},
{"learn":[3.322624921],"iteration":985,"passed_time":0.7930919983,"remaining_time":0.01126094115},
{"learn":[3.321587482],"iteration":986,"passed_time":0.7936793059,"remaining_time":0.01045372946},
{"learn":[3.318085049],"iteration":987,"passed_time":0.7942339915,"remaining_time":0.009646566698},
{"learn":[3.316506079],"iteration":988,"passed_time":0.7950856726,"remaining_time":0.008843217795},
{"learn":[3.315468587],"iteration":989,"passed_time":0.7958715601,"remaining_time":0.008039106668},
{"learn":[3.314620817],"iteration":990,"passed_time":0.7965076866,"remaining_time":0.00723367223},
{"learn":[3.3141238],"iteration":991,"passed_time":0.7971867121,"remaining_time":0.006428925097},
{"learn":[3.312901714],"iteration":992,"passed_time":0.7978819643,"remaining_time":0.005624545569},
{"learn":[3.308555886],"iteration":993,"passed_time":0.7985246987,"remaining_time":0.004820068604},
{"learn":[3.305728167],"iteration":994,"passed_time":0.7991356666,"remaining_time":0.004015757119},
{"learn":[3.304526795],"iteration":995,"passed_time":0.7997331242,"remaining_time":0.003211779615},
{"learn":[3.304464048],"iteration":996,"passed_time":0.8002948486,"remaining_time":0.002408108873},
{"learn":[3.302803266],"iteration":997,"passed_time":0.8009715862,"remaining_time":0.001605153479},
{"learn":[3.30189953],"iteration":998,"passed_time":0.801638658,"remaining_time":0.0008024410991},
{"learn":[3.301298438],"iteration":999,"passed_time":0.8022251849,"remaining_time":0}
]}